Workbook

Sheet Cleaned Data
A1: Organization | B1: Country | C1: Latitude | D1: Longitude | E1: Industry | F1: Organization size | G1: Owner | H1: Lead acquisition date | I1: Product | J1: Status | K1: Status sequence | L1: Stage | M1: Stage sequence | N1: Deal Value, $ | O1: Probability, % | P1: Expected close date | Q1: Actual close date | R1: Weighted deal value | S1: Close variance days | T1: Is open opportunity | U1: Close status | V1: Is Opportunity | W1: Is Ever Customer | X1: Is Current Customer | Y1: Is Churned | Z1: Is Won | AA1: Is Lost | AB1: Is Closed Opportunity | AC1: Probability Bucket | AD1: Probability Bucket Sort
A2: Thoughtblab | B2: Netherlands | C2: 52.370216 | D2: 4.895168 | E2: Banking and Finance | F2: Small (11-200) | G2: John Smith | H2: 45402 | I2: SAAS | J2: Churned Customer | K2: 6 | N2: 833 | O2: 90 | P2: 45511 | Q2: 45470 | R2: 749.7 | S2: -41 | T2: 0 | U2: Early | V2: 0 | W2: 1 | X2: 0 | Y2: 1 | Z2: 0 | AA2: 0 | AB2: 0 | AC2: 81–100% | AD2: 5
A3: Jaxnation | B3: Spain | C3: 40.416775 | D3: -3.70379 | E3: Energy & Utilities | F3: Small (11-200) | G3: Emily Johnson | H3: 45440 | I3: SAAS | J3: Churned Customer | K3: 6 | N3: 1623 | O3: 30 | P3: 45590 | Q3: 45546 | R3: 486.9 | S3: -44 | T3: 0 | U3: Early | V3: 0 | W3: 1 | X3: 0 | Y3: 1 | Z3: 0 | AA3: 0 | AB3: 0 | AC3: 21–40% | AD3: 2
A4: Mybuzz | B4: Italy | C4: 41.902782 | D4: 12.496366 | E4: Education & Science | F4: Small (11-200) | G4: Michael Brown | H4: 45368 | I4: SAAS | J4: Churned Customer | K4: 6 | N4: 1928 | O4: 20 | P4: 45733 | Q4: 45423 | R4: 385.6 | S4: -310 | T4: 0 | U4: Early | V4: 0 | W4: 1 | X4: 0 | Y4: 1 | Z4: 0 | AA4: 0 | AB4: 0 | AC4: 00–20% | AD4: 1
A5: Kare | B5: Germany | C5: 52.520008 | D5: 13.404954 | E5: Government Administration Healthcare | F5: Small (11-200) | G5: Michael Brown | H5: 45309 | I5: SAAS | J5: Churned Customer | K5: 6 | N5: 303 | O5: 50 | P5: 45511 | Q5: 45418 | R5: 151.5 | S5: -93 | T5: 0 | U5: Early | V5: 0 | W5: 1 | X5: 0 | Y5: 1 | Z5: 0 | AA5: 0 | AB5: 0 | AC5: 41–60% | AD5: 3
A6: Skaboo | B6: Germany | C6: 52.520008 | D6: 13.404954 | E6: Energy & Utilities | F6: Small (11-200) | G6: Michael Brown | H6: 45388 | I6: SAAS | J6: Churned Customer | K6: 6 | N6: 1911 | O6: 30 | P6: 45576 | Q6: 45498 | R6: 573.3 | S6: -78 | T6: 0 | U6: Early | V6: 0 | W6: 1 | X6: 0 | Y6: 1 | Z6: 0 | AA6: 0 | AB6: 0 | AC6: 21–40% | AD6: 2
A7: Flashset | B7: Germany | C7: 52.520008 | D7: 13.404954 | E7: Transportation & Logistics | F7: Small (11-200) | G7: Laura Thompson | H7: 45343 | I7: Custom solution | J7: Churned Customer | K7: 6 | N7: 455 | O7: 20 | P7: 45558 | Q7: 45423 | R7: 91 | S7: -135 | T7: 0 | U7: Early | V7: 0 | W7: 1 | X7: 0 | Y7: 1 | Z7: 0 | AA7: 0 | AB7: 0 | AC7: 00–20% | AD7: 1
A8: Yozio | B8: Belgium | C8: 51.260197 | D8: 4.402771 | E8: IT & IT Services | F8: Small (11-200) | G8: Laura Thompson | H8: 45335 | I8: SAAS | J8: Churned Customer | K8: 6 | N8: 351 | O8: 30 | P8: 45369 | Q8: 45399 | R8: 105.3 | S8: 30 | T8: 0 | U8: Late | V8: 0 | W8: 1 | X8: 0 | Y8: 1 | Z8: 0 | AA8: 0 | AB8: 0 | AC8: 21–40% | AD8: 2
A9: Tanoodle | B9: Switzerland | C9: 46.204391 | D9: 6.143158 | E9: IT & IT Services | F9: Small (11-200) | G9: Jessica Martinez | H9: 45306 | I9: Custom solution | J9: Churned Customer | K9: 6 | N9: 230 | O9: 70 | P9: 45429 | Q9: 45423 | R9: 161 | S9: -6 | T9: 0 | U9: Early | V9: 0 | W9: 1 | X9: 0 | Y9: 1 | Z9: 0 | AA9: 0 | AB9: 0 | AC9: 61–80% | AD9: 4
A10: Reilly, Wisozk and Stamm | B10: France | C10: 48.864716 | D10: 2.349014 | E10: Retail & Distribution | F10: Small (11-200) | G10: Michael Brown | H10: 45360 | I10: SAAS | J10: Churned Customer | K10: 6 | N10: 1697 | O10: 80 | P10: 45498 | Q10: 45473 | R10: 1357.6 | S10: -25 | T10: 0 | U10: Early | V10: 0 | W10: 1 | X10: 0 | Y10: 1 | Z10: 0 | AA10: 0 | AB10: 0 | AC10: 61–80% | AD10: 4
A11: O'Conner-Sawayn | B11: Switzerland | C11: 46.204391 | D11: 6.143158 | E11: Transportation & Logistics | F11: Small (11-200) | G11: Laura Thompson | H11: 45383 | I11: Services | J11: Churned Customer | K11: 6 | N11: 320 | O11: 60 | P11: 45436 | Q11: 45474 | R11: 192 | S11: 38 | T11: 0 | U11: Late | V11: 0 | W11: 1 | X11: 0 | Y11: 1 | Z11: 0 | AA11: 0 | AB11: 0 | AC11: 41–60% | AD11: 3
A12: Klocko-Sporer | B12: Germany | C12: 52.520008 | D12: 13.404954 | E12: Agriculture & Mining | F12: Small (11-200) | G12: Emily Johnson | H12: 45334 | I12: Custom solution | J12: Churned Customer | K12: 6 | N12: 721 | O12: 20 | P12: 45667 | Q12: 45382 | R12: 144.2 | S12: -285 | T12: 0 | U12: Early | V12: 0 | W12: 1 | X12: 0 | Y12: 1 | Z12: 0 | AA12: 0 | AB12: 0 | AC12: 00–20% | AD12: 1
A13: Borer Inc | B13: Italy | C13: 41.902782 | D13: 12.496366 | E13: Transportation & Logistics | F13: Small (11-200) | G13: Michael Brown | H13: 45351 | I13: Services | J13: Churned Customer | K13: 6 | N13: 768 | O13: 80 | P13: 45522 | Q13: 45458 | R13: 614.4 | S13: -64 | T13: 0 | U13: Early | V13: 0 | W13: 1 | X13: 0 | Y13: 1 | Z13: 0 | AA13: 0 | AB13: 0 | AC13: 61–80% | AD13: 4
... A349: Nitzsche-Cartwright | B349: Austria | C349: 48.210033 | D349: 16.363449 | E349: Government Administration Healthcare | F349: Enterprise (1001+) | G349: John Smith | H349: 45370 | I349: Custom solution | J349: Customer | K349: 5 | N349: 6762 | O349: 100 | P349: 45485 | Q349: 45425 | R349: 6762 | S349: -60 | T349: 0 | U349: Early | V349: 0 | W349: 1 | X349: 1 | Y349: 0 | Z349: 0 | AA349: 0 | AB349: 0 | AC349: 81–100% | AD349: 5
A350: Kanoodle | B350: Switzerland | C350: 46.204391 | D350: 6.143158 | E350: Transportation & Logistics | F350: Small (11-200) | G350: David Wilson | H350: 45322 | I350: Services | J350: Disqualified | K350: 7 | N350: 1214 | O350: 60 | P350: 45668 | R350: 728.4 | T350: 0 | U350: Not Closed | V350: 0 | W350: 0 | X350: 0 | Y350: 0 | Z350: 0 | AA350: 0 | AB350: 0 | AC350: 41–60% | AD350: 3
A351: Youbridge | B351: Italy | C351: 41.902782 | D351: 12.496366 | E351: Manufacturing & Production | F351: Small (11-200) | G351: Sarah Davis | H351: 45417 | I351: Services | J351: Disqualified | K351: 7 | N351: 1916 | O351: 20 | P351: 45729 | R351: 383.2 | T351: 0 | U351: Not Closed | V351: 0 | W351: 0 | X351: 0 | Y351: 0 | Z351: 0 | AA351: 0 | AB351: 0 | AC351: 00–20% | AD351: 1
A352: Jabbercube | B352: Portugal | C352: 38.736946 | D352: -9.142685 | E352: Banking and Finance | F352: Small (11-200) | G352: Laura Thompson | H352: 45442 | I352: Services | J352: Disqualified | K352: 7 | N352: 1918 | O352: 20 | P352: 45752 | R352: 383.6 | T352: 0 | U352: Not Closed | V352: 0 | W352: 0 | X352: 0 | Y352: 0 | Z352: 0 | AA352: 0 | AB352: 0 | AC352: 00–20% | AD352: 1
A353: Dabfeed | B353: Belgium | C353: 51.260197 | D353: 4.402771 | E353: Recreation & Sports | F353: Small (11-200) | G353: Emily Johnson | H353: 45407 | I353: Services | J353: Disqualified | K353: 7 | N353: 685 | O353: 60 | P353: 45743 | R353: 411 | T353: 0 | U353: Not Closed | V353: 0 | W353: 0 | X353: 0 | Y353: 0 | Z353: 0 | AA353: 0 | AB353: 0 | AC353: 41–60% | AD353: 3
A354: Skiba | B354: Switzerland | C354: 46.204391 | D354: 6.143158 | E354: Banking and Finance | F354: Small (11-200) | G354: John Smith | H354: 45364 | I354: Services | J354: Disqualified | K354: 7 | N354: 315 | O354: 40 | P354: 45636 | R354: 126 | T354: 0 | U354: Not Closed | V354: 0 | W354: 0 | X354: 0 | Y354: 0 | Z354: 0 | AA354: 0 | AB354: 0 | AC354: 21–40% | AD354: 2
A355: Voonyx | B355: Italy | C355: 41.902782 | D355: 12.496366 | E355: Banking and Finance | F355: Small (11-200) | G355: David Wilson | H355: 45294 | I355: Custom solution | J355: Disqualified | K355: 7 | N355: 810 | O355: 50 | P355: 45370 | R355: 405 | T355: 0 | U355: Not Closed | V355: 0 | W355: 0 | X355: 0 | Y355: 0 | Z355: 0 | AA355: 0 | AB355: 0 | AC355: 41–60% | AD355: 3
A356: Harber and Sons | B356: Italy | C356: 41.902782 | D356: 12.496366 | E356: IT & IT Services | F356: Small (11-200) | G356: Laura Thompson | H356: 45344 | I356: SAAS | J356: Disqualified | K356: 7 | N356: 717 | O356: 70 | P356: 45402 | R356: 501.9 | T356: 0 | U356: Not Closed | V356: 0 | W356: 0 | X356: 0 | Y356: 0 | Z356: 0 | AA356: 0 | AB356: 0 | AC356: 61–80% | AD356: 4
A357: Gorczany-Hayes | B357: Netherlands | C357: 52.370216 | D357: 4.895168 | E357: Energy & Utilities | F357: Small (11-200) | G357: Sarah Davis | H357: 45403 | I357: Services | J357: Disqualified | K357: 7 | N357: 1789 | O357: 20 | P357: 45467 | R357: 357.8 | T357: 0 | U357: Not Closed | V357: 0 | W357: 0 | X357: 0 | Y357: 0 | Z357: 0 | AA357: 0 | AB357: 0 | AC357: 00–20% | AD357: 1
A358: Ritchie Inc | B358: France | C358: 48.864716 | D358: 2.349014 | E358: Construction & Engineering | F358: Small (11-200) | G358: Michael Brown | H358: 45351 | I358: SAAS | J358: Disqualified | K358: 7 | N358: 1311 | O358: 30 | P358: 45578 | R358: 393.3 | T358: 0 | U358: Not Closed | V358: 0 | W358: 0 | X358: 0 | Y358: 0 | Z358: 0 | AA358: 0 | AB358: 0 | AC358: 21–40% | AD358: 2
A359: Strosin-Romaguera | B359: Portugal | C359: 38.736946 | D359: -9.142685 | E359: Recreation & Sports | F359: Small (11-200) | G359: Laura Thompson | H359: 45429 | I359: Services | J359: Disqualified | K359: 7 | N359: 1025 | O359: 20 | P359: 45463 | R359: 205 | T359: 0 | U359: Not Closed | V359: 0 | W359: 0 | X359: 0 | Y359: 0 | Z359: 0 | AA359: 0 | AB359: 0 | AC359: 00–20% | AD359: 1
A360: Wyman-Homenick | B360: Germany | C360: 52.520008 | D360: 13.404954 | E360: IT & IT Services | F360: Small (11-200) | G360: Jessica Martinez | H360: 45370 | I360: SAAS | J360: Disqualified | K360: 7 | N360: 1330 | O360: 30 | P360: 45549 | R360: 399 | T360: 0 | U360: Not Closed | V360: 0 | W360: 0 | X360: 0 | Y360: 0 | Z360: 0 | AA360: 0 | AB360: 0 | AC360: 21–40% | AD360: 2
A361: Koelpin, Gulgowski and Boyle | B361: Italy | C361: 41.902782 | D361: 12.496366 | E361: Recreation & Sports | F361: Small (11-200) | G361: Michael Brown | H361: 45442 | I361: Services | J361: Disqualified | K361: 7 | N361: 924 | O361: 20 | P361: 45751 | R361: 184.8 | T361: 0 | U361: Not Closed | V361: 0 | W361: 0 | X361: 0 | Y361: 0 | Z361: 0 | AA361: 0 | AB361: 0 | AC361: 00–20% | AD361: 1
... A1039: Harris and Sons | B1039: France | C1039: 48.864716 | D1039: 2.349014 | E1039: IT & IT Services | F1039: Enterprise (1001+) | G1039: Michael Brown | H1039: 45351 | I1039: Services | J1039: New | K1039: 1 | N1039: 14666 | O1039: 60 | P1039: 45564 | R1039: 8799.6 | T1039: 0 | U1039: Not Closed | V1039: 0 | W1039: 0 | X1039: 0 | Y1039: 0 | Z1039: 0 | AA1039: 0 | AB1039: 0 | AC1039: 41–60% | AD1039: 3
A1040: Flipopia | B1040: Belgium | C1040: 51.260197 | D1040: 4.402771 | E1040: Education & Science | F1040: Small (11-200) | G1040: Jessica Martinez | H1040: 45366 | I1040: Services | J1040: Opportunity | K1040: 4 | L1040: Initial contact | M1040: 2 | N1040: 1136 | O1040: 90 | P1040: 45388 | R1040: 1022.4 | T1040: 1 | U1040: Not Closed | V1040: 1 | W1040: 0 | X1040: 0 | Y1040: 0 | Z1040: 0 | AA1040: 0 | AB1040: 0 | AC1040: 81–100% | AD1040: 5
A1041: Abata | B1041: Germany | C1041: 52.520008 | D1041: 13.404954 | E1041: Banking and Finance | F1041: Small (11-200) | G1041: Sarah Davis | H1041: 45379 | I1041: SAAS | J1041: Opportunity | K1041: 4 | L1041: Initial contact | M1041: 2 | N1041: 402 | O1041: 20 | P1041: 45644 | R1041: 80.4 | T1041: 1 | U1041: Not Closed | V1041: 1 | W1041: 0 | X1041: 0 | Y1041: 0 | Z1041: 0 | AA1041: 0 | AB1041: 0 | AC1041: 00–20% | AD1041: 1
A1042: Ntags | B1042: France | C1042: 48.864716 | D1042: 2.349014 | E1042: Energy & Utilities | F1042: Small (11-200) | G1042: Jessica Martinez | H1042: 45350 | I1042: Custom solution | J1042: Opportunity | K1042: 4 | L1042: Initial contact | M1042: 2 | N1042: 1210 | O1042: 30 | P1042: 45624 | R1042: 363 | T1042: 1 | U1042: Not Closed | V1042: 1 | W1042: 0 | X1042: 0 | Y1042: 0 | Z1042: 0 | AA1042: 0 | AB1042: 0 | AC1042: 21–40% | AD1042: 2
A1043: Skippad | B1043: Italy | C1043: 41.902782 | D1043: 12.496366 | E1043: Transportation & Logistics | F1043: Small (11-200) | G1043: Kevin Anderson | H1043: 45415 | I1043: Services | J1043: Opportunity | K1043: 4 | L1043: Initial contact | M1043: 2 | N1043: 1626 | O1043: 40 | P1043: 45568 | R1043: 650.4 | T1043: 1 | U1043: Not Closed | V1043: 1 | W1043: 0 | X1043: 0 | Y1043: 0 | Z1043: 0 | AA1043: 0 | AB1043: 0 | AC1043: 21–40% | AD1043: 2
A1044: Aivee | B1044: Switzerland | C1044: 46.204391 | D1044: 6.143158 | E1044: Transportation & Logistics | F1044: Small (11-200) | G1044: John Smith | H1044: 45295 | I1044: Services | J1044: Opportunity | K1044: 4 | L1044: Initial contact | M1044: 2 | N1044: 785 | O1044: 60 | P1044: 45343 | R1044: 471 | T1044: 1 | U1044: Not Closed | V1044: 1 | W1044: 0 | X1044: 0 | Y1044: 0 | Z1044: 0 | AA1044: 0 | AB1044: 0 | AC1044: 41–60% | AD1044: 3
A1045: Youspan | B1045: France | C1045: 48.864716 | D1045: 2.349014 | E1045: Entertainment & Media & Hospitality | F1045: Small (11-200) | G1045: Laura Thompson | H1045: 45299 | I1045: Services | J1045: Opportunity | K1045: 4 | L1045: Initial contact | M1045: 2 | N1045: 1380 | O1045: 30 | P1045: 45641 | R1045: 414 | T1045: 1 | U1045: Not Closed | V1045: 1 | W1045: 0 | X1045: 0 | Y1045: 0 | Z1045: 0 | AA1045: 0 | AB1045: 0 | AC1045: 21–40% | AD1045: 2
A1046: Realfire | B1046: Spain | C1046: 40.416775 | D1046: -3.70379 | E1046: Retail & Distribution | F1046: Small (11-200) | G1046: Jessica Martinez | H1046: 45415 | I1046: Services | J1046: Opportunity | K1046: 4 | L1046: Initial contact | M1046: 2 | N1046: 1885 | O1046: 70 | P1046: 45580 | R1046: 1319.5 | T1046: 1 | U1046: Not Closed | V1046: 1 | W1046: 0 | X1046: 0 | Y1046: 0 | Z1046: 0 | AA1046: 0 | AB1046: 0 | AC1046: 61–80% | AD1046: 4
A1047: Quinu | B1047: Switzerland | C1047: 46.204391 | D1047: 6.143158 | E1047: IT & IT Services | F1047: Small (11-200) | G1047: Laura Thompson | H1047: 45320 | I1047: Services | J1047: Opportunity | K1047: 4 | L1047: Initial contact | M1047: 2 | N1047: 1320 | O1047: 70 | P1047: 45342 | R1047: 924 | T1047: 1 | U1047: Not Closed | V1047: 1 | W1047: 0 | X1047: 0 | Y1047: 0 | Z1047: 0 | AA1047: 0 | AB1047: 0 | AC1047: 61–80% | AD1047: 4
A1048: Devpulse | B1048: Portugal | C1048: 38.736946 | D1048: -9.142685 | E1048: Transportation & Logistics | F1048: Small (11-200) | G1048: Michael Brown | H1048: 45354 | I1048: Services | J1048: Opportunity | K1048: 4 | L1048: Initial contact | M1048: 2 | N1048: 683 | O1048: 100 | P1048: 45625 | R1048: 683 | T1048: 1 | U1048: Not Closed | V1048: 1 | W1048: 0 | X1048: 0 | Y1048: 0 | Z1048: 0 | AA1048: 0 | AB1048: 0 | AC1048: 81–100% | AD1048: 5
A1049: Skiptube | B1049: Switzerland | C1049: 46.204391 | D1049: 6.143158 | E1049: Transportation & Logistics | F1049: Small (11-200) | G1049: Laura Thompson | H1049: 45375 | I1049: Services | J1049: Opportunity | K1049: 4 | L1049: Initial contact | M1049: 2 | N1049: 909 | O1049: 40 | P1049: 45411 | R1049: 363.6 | T1049: 1 | U1049: Not Closed | V1049: 1 | W1049: 0 | X1049: 0 | Y1049: 0 | Z1049: 0 | AA1049: 0 | AB1049: 0 | AC1049: 21–40% | AD1049: 2
A1050: Skyndu | B1050: Germany | C1050: 52.520008 | D1050: 13.404954 | E1050: Banking and Finance | F1050: Small (11-200) | G1050: Jessica Martinez | H1050: 45315 | I1050: SAAS | J1050: Opportunity | K1050: 4 | L1050: Initial contact | M1050: 2 | N1050: 673 | O1050: 60 | P1050: 45647 | R1050: 403.8 | T1050: 1 | U1050: Not Closed | V1050: 1 | W1050: 0 | X1050: 0 | Y1050: 0 | Z1050: 0 | AA1050: 0 | AB1050: 0 | AC1050: 41–60% | AD1050: 3
A1051: Steuber-Lowe | B1051: Belgium | C1051: 51.260197 | D1051: 4.402771 | E1051: Government Administration Healthcare | F1051: Small (11-200) | G1051: John Smith | H1051: 45388 | I1051: Custom solution | J1051: Opportunity | K1051: 4 | L1051: Initial contact | M1051: 2 | N1051: 1498 | O1051: 60 | P1051: 45496 | R1051: 898.8 | T1051: 1 | U1051: Not Closed | V1051: 1 | W1051: 0 | X1051: 0 | Y1051: 0 | Z1051: 0 | AA1051: 0 | AB1051: 0 | AC1051: 41–60% | AD1051: 3
... A1906: Wunsch Group | B1906: Germany | C1906: 52.520008 | D1906: 13.404954 | E1906: Banking and Finance | F1906: Enterprise (1001+) | G1906: Michael Brown | H1906: 45332 | I1906: Custom solution | J1906: Opportunity | K1906: 4 | L1906: Won | M1906: 5 | N1906: 5433 | O1906: 30 | P1906: 45414 | R1906: 1629.9 | T1906: 0 | U1906: Not Closed | V1906: 1 | W1906: 0 | X1906: 0 | Y1906: 0 | Z1906: 1 | AA1906: 0 | AB1906: 1 | AC1906: 21–40% | AD1906: 2
A1907: Twitterworks | B1907: Germany | C1907: 52.520008 | D1907: 13.404954 | E1907: Transportation & Logistics | F1907: Small (11-200) | G1907: Kevin Anderson | H1907: 45380 | I1907: Services | J1907: Qualified | K1907: 2 | N1907: 1044 | O1907: 40 | P1907: 45718 | R1907: 417.6 | T1907: 0 | U1907: Not Closed | V1907: 0 | W1907: 0 | X1907: 0 | Y1907: 0 | Z1907: 0 | AA1907: 0 | AB1907: 0 | AC1907: 21–40% | AD1907: 2
A1908: Demizz | B1908: Germany | C1908: 52.520008 | D1908: 13.404954 | E1908: Government Administration Healthcare | F1908: Small (11-200) | G1908: Michael Brown | H1908: 45397 | I1908: Custom solution | J1908: Qualified | K1908: 2 | N1908: 1251 | O1908: 30 | P1908: 45494 | R1908: 375.3 | T1908: 0 | U1908: Not Closed | V1908: 0 | W1908: 0 | X1908: 0 | Y1908: 0 | Z1908: 0 | AA1908: 0 | AB1908: 0 | AC1908: 21–40% | AD1908: 2
A1909: Voomm | B1909: Spain | C1909: 40.416775 | D1909: -3.70379 | E1909: IT & IT Services | F1909: Small (11-200) | G1909: Laura Thompson | H1909: 45324 | I1909: SAAS | J1909: Qualified | K1909: 2 | N1909: 1825 | O1909: 60 | P1909: 45467 | R1909: 1095 | T1909: 0 | U1909: Not Closed | V1909: 0 | W1909: 0 | X1909: 0 | Y1909: 0 | Z1909: 0 | AA1909: 0 | AB1909: 0 | AC1909: 41–60% | AD1909: 3
A1910: Zazio | B1910: Italy | C1910: 41.902782 | D1910: 12.496366 | E1910: IT & IT Services | F1910: Small (11-200) | G1910: Michael Brown | H1910: 45293 | I1910: Services | J1910: Qualified | K1910: 2 | N1910: 1812 | O1910: 80 | P1910: 45380 | R1910: 1449.6 | T1910: 0 | U1910: Not Closed | V1910: 0 | W1910: 0 | X1910: 0 | Y1910: 0 | Z1910: 0 | AA1910: 0 | AB1910: 0 | AC1910: 61–80% | AD1910: 4
A1911: Bubblebox | B1911: France | C1911: 48.864716 | D1911: 2.349014 | E1911: Government Administration Healthcare | F1911: Small (11-200) | G1911: Jessica Martinez | H1911: 45411 | I1911: SAAS | J1911: Qualified | K1911: 2 | N1911: 1948 | O1911: 70 | P1911: 45740 | R1911: 1363.6 | T1911: 0 | U1911: Not Closed | V1911: 0 | W1911: 0 | X1911: 0 | Y1911: 0 | Z1911: 0 | AA1911: 0 | AB1911: 0 | AC1911: 61–80% | AD1911: 4
A1912: Chatterbridge | B1912: Portugal | C1912: 38.736946 | D1912: -9.142685 | E1912: IT & IT Services | F1912: Small (11-200) | G1912: Jessica Martinez | H1912: 45313 | I1912: SAAS | J1912: Qualified | K1912: 2 | N1912: 978 | O1912: 20 | P1912: 45535 | R1912: 195.6 | T1912: 0 | U1912: Not Closed | V1912: 0 | W1912: 0 | X1912: 0 | Y1912: 0 | Z1912: 0 | AA1912: 0 | AB1912: 0 | AC1912: 00–20% | AD1912: 1
A1913: Linkbridge | B1913: Portugal | C1913: 38.736946 | D1913: -9.142685 | E1913: Telecommunications | F1913: Small (11-200) | G1913: Jessica Martinez | H1913: 45363 | I1913: SAAS | J1913: Qualified | K1913: 2 | N1913: 1815 | O1913: 70 | P1913: 45685 | R1913: 1270.5 | T1913: 0 | U1913: Not Closed | V1913: 0 | W1913: 0 | X1913: 0 | Y1913: 0 | Z1913: 0 | AA1913: 0 | AB1913: 0 | AC1913: 61–80% | AD1913: 4
A1914: DabZ | B1914: Italy | C1914: 41.902782 | D1914: 12.496366 | E1914: Telecommunications | F1914: Small (11-200) | G1914: Jessica Martinez | H1914: 45311 | I1914: SAAS | J1914: Qualified | K1914: 2 | N1914: 879 | O1914: 100 | P1914: 45470 | R1914: 879 | T1914: 0 | U1914: Not Closed | V1914: 0 | W1914: 0 | X1914: 0 | Y1914: 0 | Z1914: 0 | AA1914: 0 | AB1914: 0 | AC1914: 81–100% | AD1914: 5
A1915: Gabvine | B1915: France | C1915: 48.864716 | D1915: 2.349014 | E1915: Telecommunications | F1915: Small (11-200) | G1915: John Smith | H1915: 45352 | I1915: Services | J1915: Qualified | K1915: 2 | N1915: 665 | O1915: 40 | P1915: 45474 | R1915: 266 | T1915: 0 | U1915: Not Closed | V1915: 0 | W1915: 0 | X1915: 0 | Y1915: 0 | Z1915: 0 | AA1915: 0 | AB1915: 0 | AC1915: 21–40% | AD1915: 2
A1916: Voolith | B1916: Italy | C1916: 41.902782 | D1916: 12.496366 | E1916: Transportation & Logistics | F1916: Small (11-200) | G1916: Laura Thompson | H1916: 45443 | I1916: SAAS | J1916: Qualified | K1916: 2 | N1916: 268 | O1916: 40 | P1916: 45466 | R1916: 107.2 | T1916: 0 | U1916: Not Closed | V1916: 0 | W1916: 0 | X1916: 0 | Y1916: 0 | Z1916: 0 | AA1916: 0 | AB1916: 0 | AC1916: 21–40% | AD1916: 2
A1917: Eire | B1917: Italy | C1917: 41.902782 | D1917: 12.496366 | E1917: Manufacturing & Production | F1917: Small (11-200) | G1917: Kevin Anderson | H1917: 45406 | I1917: Custom solution | J1917: Qualified | K1917: 2 | N1917: 1387 | O1917: 50 | P1917: 45702 | R1917: 693.5 | T1917: 0 | U1917: Not Closed | V1917: 0 | W1917: 0 | X1917: 0 | Y1917: 0 | Z1917: 0 | AA1917: 0 | AB1917: 0 | AC1917: 41–60% | AD1917: 3
A1918: Devpoint | B1918: Belgium | C1918: 51.260197 | D1918: 4.402771 | E1918: Education & Science | F1918: Small (11-200) | G1918: David Wilson | H1918: 45352 | I1918: SAAS | J1918: Qualified | K1918: 2 | N1918: 207 | O1918: 40 | P1918: 45539 | R1918: 82.8 | T1918: 0 | U1918: Not Closed | V1918: 0 | W1918: 0 | X1918: 0 | Y1918: 0 | Z1918: 0 | AA1918: 0 | AB1918: 0 | AC1918: 21–40% | AD1918: 2
... A3001: Lang-Mraz | B3001: Switzerland | C3001: 46.204391 | D3001: 6.143158 | E3001: Banking and Finance | F3001: Enterprise (1001+) | G3001: Laura Thompson | H3001: 45432 | I3001: Custom solution | J3001: Sales Accepted | K3001: 3 | N3001: 2680 | O3001: 20 | P3001: 45535 | R3001: 536 | T3001: 0 | U3001: Not Closed | V3001: 0 | W3001: 0 | X3001: 0 | Y3001: 0 | Z3001: 0 | AA3001: 0 | AB3001: 0 | AC3001: 00–20% | AD3001: 1

Sheet Analysis 1 — Descriptive statis
A3: Probability , % | B3: Count | C3: Mean | D3: Median Probability | E3: StdDev | F3: Min of Probability, % | G3: Max of Probability, % | H3: Q1 Probability | I3: Q3 Probability
A4: Lost | B4: 61 | C4: 42.295082 | D4: 40 | E4: 21.086603 | F4: 10 | G4: 100 | H4: 30 | I4: 50
A5: Won | B5: 83 | C5: 43.855422 | D5: 40 | E5: 21.910646 | F5: 10 | G5: 100 | H5: 30 | I5: 60
A6: Grand Total | B6: 144 | C6: 43.194444 | D6: 40 | E6: 21.504684 | F6: 10 | G6: 100 | H6: 30 | I6: 60
A11: Count of Organization | B11: Column Labels
A12: Probability , % | B12: Lost | C12: Won | D12: Grand Total
A13: 10 | B13: 0.032786885 | C13: 0.048192771 | D13: 0.041666667
A14: 20 | B14: 0.19672131 | C14: 0.19277108 | D14: 0.19444444
A15: 30 | B15: 0.18032787 | C15: 0.14457831 | D15: 0.15972222
A16: 40 | B16: 0.2295082 | C16: 0.19277108 | D16: 0.20833333
A17: 50 | B17: 0.14754098 | C17: 0.10843373 | D17: 0.125
A18: 60 | B18: 0.049180328 | C18: 0.1686747 | D18: 0.11805556
A19: 70 | B19: 0.081967213 | C19: 0.048192771 | D19: 0.0625
A20: 80 | B20: 0.016393443 | C20: 0.024096386 | D20: 0.020833333
A21: 90 | B21: 0.049180328 | C21: 0.060240964 | D21: 0.055555556
A22: 100 | B22: 0.016393443 | C22: 0.012048193 | D22: 0.013888889
A23: Grand Total | B23: 1 | C23: 1 | D23: 1
B25: Lost | C25: Won
B26: {=_xlfn._xlws.FILTER( Cleaned_Data[Probability, %], ( Cleaned_Data[Status]="Opportunity")* ( Cleaned_Data[Stage]="Lost") )} -> 30 | C26: {=_xlfn._xlws.FILTER( Cleaned_Data[Probability, %], ( Cleaned_Data[Status]="Opportunity")* ( Cleaned_Data[Stage]="Won") )} -> 20
B27: 20 | C27: 20
B28: 50 | C28: 20
B29: 30 | C29: 40
B30: 50 | C30: 10
B31: 20 | C31: 20
B32: 30 | C32: 20
B33: 50 | C33: 60
B34: 20 | C34: 60
B35: 20 | C35: 60
B36: 40 | C36: 90
B37: 20 | C37: 30
B38: 40 | C38: 40
... B86: 40 | C86: 40
C87: 20
C88: 60
C89: 20
C90: 30
C91: 60
C92: 30
C93: 60
C94: 30
C95: 40
C96: 40
C97: 30
C98: 40
... C108: 30
A110: NHẬN XÉT
A111: STT | B111: NHẬN XÉT | C111: Ghi chú | E111: INSIGHT
A112: 1 | B112: Mean gần như bằng nhau | C112: Won: 43.86% | D112: Lost: 42.30% | E112: Chưa thấy separation rõ ràng.
A113: 2 | B113: Cả 2 có Median=40% bằng nhau | E113: Một opportunity có Probability khoảng 40%, từ descriptive analysis hiện tại chúng ta không thấy tín hiệu rõ rằng nó thuộc Won hay Lost.
A114: 3 | B114: Boxplot overlap mạnh | E114: Chưa có separation rõ.
A115: 4 | B115: Ở mức Probability = 60%: Lost: 4.92% Won: 18.07% | C115: Khác biệt rõ ràng nhất | E115: Chưa đủ chứng minh Probability đáng tin cậy
A116: 5 | B116: Boxplot còn phát hiện Outlier ở Lost | C116: Probability 90% và 100% nhưng vẫn Lost
A118: KẾT LUẬN
A119: Cần inferential statistics để xác định có đủ bằng chứng để cho rằng Won opportunities thực sự có Probability cao hơn Lost opportunities hay không.
A120: Hiện tại trường Probability chưa đáng tin cậy

Sheet Analysis 2 — Hypothesis Testing
A1: Stage của Won/Lost | B1: Probability, % | C1: Rank | E1: Metric | F1: Value | H1: H0 | M1: Won Probability | N1: Lost Probability | P1: Bootstrap Mean Difference | Q1: Bootstrap lower CI | R1: Bootstrap upper CI
A2: {=_xlfn._xlws.FILTER( Cleaned_Data[Stage], ( Cleaned_Data[Status]="Opportunity")* (( Cleaned_Data[Stage]="Lost" )+( Cleaned_Data[Stage]="Won" )) )} -> Lost | B2: {=_xlfn._xlws.FILTER( Cleaned_Data[Probability, %], ( Cleaned_Data[Status]="Opportunity")* (( Cleaned_Data[Stage]="Lost" )+( Cleaned_Data[Stage]="Won" )) )} -> 30 | C2: =_xlfn.RANK.AVG(B2,$B$2:$B$145,1) -> 46 | E2: Won N | F2: =COUNTIF(_xlfn.ANCHORARRAY($A$2),"Won") -> 83 | M2: {=_xlfn._xlws.FILTER($B$2:$B$145,$A$2:$A$145="Won")} -> 20 | N2: {=_xlfn._xlws.FILTER($B$2:$B$145,$A$2:$A$145="Lost")} -> 30 | P2: {=AVERAGE( INDEX(_xlfn.ANCHORARRAY($M$2),_xlfn.RANDARRAY(ROWS(_xlfn.ANCHORARRAY($M$2)),1,1,ROWS(_xlfn.ANCHORARRAY($M$2)),TRUE)) ) - AVERAGE( INDEX(_xlfn.ANCHORARRAY($N$2),_xlfn.RANDARRAY(ROWS(_xlfn.ANCHORARRAY($N$2)),1,1,ROWS(_xlfn.ANCHORARRAY($N$2)),TRUE)) )} -> -2.0837448 | Q2: =_xlfn.PERCENTILE.INC(P2:P1001,0.025) -> -5.6953387 | R2: =_xlfn.PERCENTILE.INC(P2:P1001,0.975) -> 8.4636085
A3: Lost | B3: 20 | C3: =_xlfn.RANK.AVG(B3,$B$2:$B$145,1) -> 20.5 | E3: Lost N | F3: =COUNTIF(_xlfn.ANCHORARRAY($A$2),"Lost") -> 61 | H3: Probability của Won không có xu hướng cao hơn Lost. | M3: 20 | N3: 20 | P3: {=AVERAGE( INDEX(_xlfn.ANCHORARRAY($M$2),_xlfn.RANDARRAY(ROWS(_xlfn.ANCHORARRAY($M$2)),1,1,ROWS(_xlfn.ANCHORARRAY($M$2)),TRUE)) ) - AVERAGE( INDEX(_xlfn.ANCHORARRAY($N$2),_xlfn.RANDARRAY(ROWS(_xlfn.ANCHORARRAY($N$2)),1,1,ROWS(_xlfn.ANCHORARRAY($N$2)),TRUE)) )} -> 3.8396208
A4: Lost | B4: 50 | C4: =_xlfn.RANK.AVG(B4,$B$2:$B$145,1) -> 96.5 | E4: Mean Won | F4: =AVERAGEIF(_xlfn.ANCHORARRAY($A$2),"Won",_xlfn.ANCHORARRAY( $B$2)) -> 43.855422 | M4: 20 | N4: 50 | P4: {=AVERAGE( INDEX(_xlfn.ANCHORARRAY($M$2),_xlfn.RANDARRAY(ROWS(_xlfn.ANCHORARRAY($M$2)),1,1,ROWS(_xlfn.ANCHORARRAY($M$2)),TRUE)) ) - AVERAGE( INDEX(_xlfn.ANCHORARRAY($N$2),_xlfn.RANDARRAY(ROWS(_xlfn.ANCHORARRAY($N$2)),1,1,ROWS(_xlfn.ANCHORARRAY($N$2)),TRUE)) )} -> 3.9324511
A5: Lost | B5: 30 | C5: =_xlfn.RANK.AVG(B5,$B$2:$B$145,1) -> 46 | E5: Mean Lost | F5: =AVERAGEIF(_xlfn.ANCHORARRAY($A$2),"Lost",_xlfn.ANCHORARRAY( $B$2)) -> 42.295082 | H5: H1 | M5: 40 | N5: 30 | P5: {=AVERAGE( INDEX(_xlfn.ANCHORARRAY($M$2),_xlfn.RANDARRAY(ROWS(_xlfn.ANCHORARRAY($M$2)),1,1,ROWS(_xlfn.ANCHORARRAY($M$2)),TRUE)) ) - AVERAGE( INDEX(_xlfn.ANCHORARRAY($N$2),_xlfn.RANDARRAY(ROWS(_xlfn.ANCHORARRAY($N$2)),1,1,ROWS(_xlfn.ANCHORARRAY($N$2)),TRUE)) )} -> 0.39897294
A6: Lost | B6: 50 | C6: =_xlfn.RANK.AVG(B6,$B$2:$B$145,1) -> 96.5 | E6: Median Won | F6: {=MEDIAN(_xlfn._xlws.FILTER(_xlfn.ANCHORARRAY($B$2),_xlfn.ANCHORARRAY($A$2)="Won"))} -> 40 | M6: 10 | N6: 50 | P6: {=AVERAGE( INDEX(_xlfn.ANCHORARRAY($M$2),_xlfn.RANDARRAY(ROWS(_xlfn.ANCHORARRAY($M$2)),1,1,ROWS(_xlfn.ANCHORARRAY($M$2)),TRUE)) ) - AVERAGE( INDEX(_xlfn.ANCHORARRAY($N$2),_xlfn.RANDARRAY(ROWS(_xlfn.ANCHORARRAY($N$2)),1,1,ROWS(_xlfn.ANCHORARRAY($N$2)),TRUE)) )} -> -2.295082
A7: Lost | B7: 20 | C7: =_xlfn.RANK.AVG(B7,$B$2:$B$145,1) -> 20.5 | E7: Median Lost | F7: {=MEDIAN(_xlfn._xlws.FILTER(_xlfn.ANCHORARRAY($B$2),_xlfn.ANCHORARRAY($A$2)="Lost"))} -> 40 | H7: Probability của Won có xu hướng cao hơn Lost. | M7: 20 | N7: 20 | P7: {=AVERAGE( INDEX(_xlfn.ANCHORARRAY($M$2),_xlfn.RANDARRAY(ROWS(_xlfn.ANCHORARRAY($M$2)),1,1,ROWS(_xlfn.ANCHORARRAY($M$2)),TRUE)) ) - AVERAGE( INDEX(_xlfn.ANCHORARRAY($N$2),_xlfn.RANDARRAY(ROWS(_xlfn.ANCHORARRAY($N$2)),1,1,ROWS(_xlfn.ANCHORARRAY($N$2)),TRUE)) )} -> 1.4872605
A8: Lost | B8: 30 | C8: =_xlfn.RANK.AVG(B8,$B$2:$B$145,1) -> 46 | E8: SD Won | F8: {=_xlfn.STDEV.S(_xlfn._xlws.FILTER($B$2:$B$145,$A$2:$A$145="Won"))} -> 21.910646 | M8: 20 | N8: 30 | P8: {=AVERAGE( INDEX(_xlfn.ANCHORARRAY($M$2),_xlfn.RANDARRAY(ROWS(_xlfn.ANCHORARRAY($M$2)),1,1,ROWS(_xlfn.ANCHORARRAY($M$2)),TRUE)) ) - AVERAGE( INDEX(_xlfn.ANCHORARRAY($N$2),_xlfn.RANDARRAY(ROWS(_xlfn.ANCHORARRAY($N$2)),1,1,ROWS(_xlfn.ANCHORARRAY($N$2)),TRUE)) )} -> -5.6428995
A9: Lost | B9: 50 | C9: =_xlfn.RANK.AVG(B9,$B$2:$B$145,1) -> 96.5 | E9: SD Lost | F9: {=_xlfn.STDEV.S(_xlfn._xlws.FILTER($B$2:$B$145,$A$2:$A$145="Lost"))} -> 21.086603 | H9: Và α = 0.05 | M9: 60 | N9: 50 | P9: {=AVERAGE( INDEX(_xlfn.ANCHORARRAY($M$2),_xlfn.RANDARRAY(ROWS(_xlfn.ANCHORARRAY($M$2)),1,1,ROWS(_xlfn.ANCHORARRAY($M$2)),TRUE)) ) - AVERAGE( INDEX(_xlfn.ANCHORARRAY($N$2),_xlfn.RANDARRAY(ROWS(_xlfn.ANCHORARRAY($N$2)),1,1,ROWS(_xlfn.ANCHORARRAY($N$2)),TRUE)) )} -> 9.0065179
A10: Lost | B10: 20 | C10: =_xlfn.RANK.AVG(B10,$B$2:$B$145,1) -> 20.5 | E10: Mean Difference | F10: =F4-F5 -> 1.5603397 | H10: Chúng ta dùng one-sided Mann–Whitney U test. | M10: 60 | N10: 20 | P10: {=AVERAGE( INDEX(_xlfn.ANCHORARRAY($M$2),_xlfn.RANDARRAY(ROWS(_xlfn.ANCHORARRAY($M$2)),1,1,ROWS(_xlfn.ANCHORARRAY($M$2)),TRUE)) ) - AVERAGE( INDEX(_xlfn.ANCHORARRAY($N$2),_xlfn.RANDARRAY(ROWS(_xlfn.ANCHORARRAY($N$2)),1,1,ROWS(_xlfn.ANCHORARRAY($N$2)),TRUE)) )} -> 6.6067549
A11: Lost | B11: 20 | C11: =_xlfn.RANK.AVG(B11,$B$2:$B$145,1) -> 20.5 | M11: 60 | N11: 20 | P11: {=AVERAGE( INDEX(_xlfn.ANCHORARRAY($M$2),_xlfn.RANDARRAY(ROWS(_xlfn.ANCHORARRAY($M$2)),1,1,ROWS(_xlfn.ANCHORARRAY($M$2)),TRUE)) ) - AVERAGE( INDEX(_xlfn.ANCHORARRAY($N$2),_xlfn.RANDARRAY(ROWS(_xlfn.ANCHORARRAY($N$2)),1,1,ROWS(_xlfn.ANCHORARRAY($N$2)),TRUE)) )} -> 5.56587
A12: Lost | B12: 40 | C12: =_xlfn.RANK.AVG(B12,$B$2:$B$145,1) -> 72.5 | E12: One-sided Mann–Whitney U test | M12: 90 | N12: 40 | P12: {=AVERAGE( INDEX(_xlfn.ANCHORARRAY($M$2),_xlfn.RANDARRAY(ROWS(_xlfn.ANCHORARRAY($M$2)),1,1,ROWS(_xlfn.ANCHORARRAY($M$2)),TRUE)) ) - AVERAGE( INDEX(_xlfn.ANCHORARRAY($N$2),_xlfn.RANDARRAY(ROWS(_xlfn.ANCHORARRAY($N$2)),1,1,ROWS(_xlfn.ANCHORARRAY($N$2)),TRUE)) )} -> 4.799526
A13: Lost | B13: 20 | C13: =_xlfn.RANK.AVG(B13,$B$2:$B$145,1) -> 20.5 | E13: Rank Sum Won | F13: =SUMIF(_xlfn.ANCHORARRAY($A$2),"Won",$C$2:$C$145) -> 6128.5 | M13: 30 | N13: 20 | P13: {=AVERAGE( INDEX(_xlfn.ANCHORARRAY($M$2),_xlfn.RANDARRAY(ROWS(_xlfn.ANCHORARRAY($M$2)),1,1,ROWS(_xlfn.ANCHORARRAY($M$2)),TRUE)) ) - AVERAGE( INDEX(_xlfn.ANCHORARRAY($N$2),_xlfn.RANDARRAY(ROWS(_xlfn.ANCHORARRAY($N$2)),1,1,ROWS(_xlfn.ANCHORARRAY($N$2)),TRUE)) )} -> 0.96188031
A14: Lost | B14: 40 | C14: =_xlfn.RANK.AVG(B14,$B$2:$B$145,1) -> 72.5 | E14: U Won | F14: =F13-F2*(F2+1)/2 -> 2642.5 | G14: Ta có U Won > Expected U, Won có cao hơn một chút | M14: 40 | N14: 40 | P14: {=AVERAGE( INDEX(_xlfn.ANCHORARRAY($M$2),_xlfn.RANDARRAY(ROWS(_xlfn.ANCHORARRAY($M$2)),1,1,ROWS(_xlfn.ANCHORARRAY($M$2)),TRUE)) ) - AVERAGE( INDEX(_xlfn.ANCHORARRAY($N$2),_xlfn.RANDARRAY(ROWS(_xlfn.ANCHORARRAY($N$2)),1,1,ROWS(_xlfn.ANCHORARRAY($N$2)),TRUE)) )} -> 3.6756864
A15: Lost | B15: 20 | C15: =_xlfn.RANK.AVG(B15,$B$2:$B$145,1) -> 20.5 | E15: U Lost | F15: =F2*F3-F14 -> 2420.5 | M15: 60 | N15: 20 | P15: {=AVERAGE( INDEX(_xlfn.ANCHORARRAY($M$2),_xlfn.RANDARRAY(ROWS(_xlfn.ANCHORARRAY($M$2)),1,1,ROWS(_xlfn.ANCHORARRAY($M$2)),TRUE)) ) - AVERAGE( INDEX(_xlfn.ANCHORARRAY($N$2),_xlfn.RANDARRAY(ROWS(_xlfn.ANCHORARRAY($N$2)),1,1,ROWS(_xlfn.ANCHORARRAY($N$2)),TRUE)) )} -> 2.1429982
A16: Lost | B16: 40 | C16: =_xlfn.RANK.AVG(B16,$B$2:$B$145,1) -> 72.5 | E16: Expected U | F16: =F2*F3/2 -> 2531.5 | M16: 60 | N16: 40 | P16: {=AVERAGE( INDEX(_xlfn.ANCHORARRAY($M$2),_xlfn.RANDARRAY(ROWS(_xlfn.ANCHORARRAY($M$2)),1,1,ROWS(_xlfn.ANCHORARRAY($M$2)),TRUE)) ) - AVERAGE( INDEX(_xlfn.ANCHORARRAY($N$2),_xlfn.RANDARRAY(ROWS(_xlfn.ANCHORARRAY($N$2)),1,1,ROWS(_xlfn.ANCHORARRAY($N$2)),TRUE)) )} -> 4.5980644
A17: Lost | B17: 30 | C17: =_xlfn.RANK.AVG(B17,$B$2:$B$145,1) -> 46 | E17: Tie Sum | F17: {=SUMPRODUCT(COUNTIF($B$2:$B$145,$B$2:$B$145)^2-1)} -> 73212 | M17: 10 | N17: 30 | P17: {=AVERAGE( INDEX(_xlfn.ANCHORARRAY($M$2),_xlfn.RANDARRAY(ROWS(_xlfn.ANCHORARRAY($M$2)),1,1,ROWS(_xlfn.ANCHORARRAY($M$2)),TRUE)) ) - AVERAGE( INDEX(_xlfn.ANCHORARRAY($N$2),_xlfn.RANDARRAY(ROWS(_xlfn.ANCHORARRAY($N$2)),1,1,ROWS(_xlfn.ANCHORARRAY($N$2)),TRUE)) )} -> -1.3845546
A18: Lost | B18: 50 | C18: =_xlfn.RANK.AVG(B18,$B$2:$B$145,1) -> 96.5 | E18: SD(U) | F18: =SQRT( F2*F3/12* ( (F2+F3+1) - F17/((F2+F3)*(F2+F3-1)) ) ) -> 244.2905 | M18: 20 | N18: 50 | P18: {=AVERAGE( INDEX(_xlfn.ANCHORARRAY($M$2),_xlfn.RANDARRAY(ROWS(_xlfn.ANCHORARRAY($M$2)),1,1,ROWS(_xlfn.ANCHORARRAY($M$2)),TRUE)) ) - AVERAGE( INDEX(_xlfn.ANCHORARRAY($N$2),_xlfn.RANDARRAY(ROWS(_xlfn.ANCHORARRAY($N$2)),1,1,ROWS(_xlfn.ANCHORARRAY($N$2)),TRUE)) )} -> 3.0930278
A19: Lost | B19: 40 | C19: =_xlfn.RANK.AVG(B19,$B$2:$B$145,1) -> 72.5 | E19: Z | F19: =(F14-F16-0.5*SIGN(F14-F16))/F18 -> 0.45233031 | G19: Tức là observed U chỉ cách null expectation khoảng 0.45 standard deviations, không nhiều. | M19: 20 | N19: 40 | P19: {=AVERAGE( INDEX(_xlfn.ANCHORARRAY($M$2),_xlfn.RANDARRAY(ROWS(_xlfn.ANCHORARRAY($M$2)),1,1,ROWS(_xlfn.ANCHORARRAY($M$2)),TRUE)) ) - AVERAGE( INDEX(_xlfn.ANCHORARRAY($N$2),_xlfn.RANDARRAY(ROWS(_xlfn.ANCHORARRAY($N$2)),1,1,ROWS(_xlfn.ANCHORARRAY($N$2)),TRUE)) )} -> -2.9409441
A20: Lost | B20: 40 | C20: =_xlfn.RANK.AVG(B20,$B$2:$B$145,1) -> 72.5 | E20: p-value | F20: =1-_xlfn.NORM.S.DIST(F19,TRUE) -> 0.32551552 | G20: Vì p-value > α nên Fail to reject H0 | M20: 20 | N20: 40 | P20: {=AVERAGE( INDEX(_xlfn.ANCHORARRAY($M$2),_xlfn.RANDARRAY(ROWS(_xlfn.ANCHORARRAY($M$2)),1,1,ROWS(_xlfn.ANCHORARRAY($M$2)),TRUE)) ) - AVERAGE( INDEX(_xlfn.ANCHORARRAY($N$2),_xlfn.RANDARRAY(ROWS(_xlfn.ANCHORARRAY($N$2)),1,1,ROWS(_xlfn.ANCHORARRAY($N$2)),TRUE)) )} -> -3.3675686
A21: Lost | B21: 40 | C21: =_xlfn.RANK.AVG(B21,$B$2:$B$145,1) -> 72.5 | M21: 30 | N21: 40 | P21: {=AVERAGE( INDEX(_xlfn.ANCHORARRAY($M$2),_xlfn.RANDARRAY(ROWS(_xlfn.ANCHORARRAY($M$2)),1,1,ROWS(_xlfn.ANCHORARRAY($M$2)),TRUE)) ) - AVERAGE( INDEX(_xlfn.ANCHORARRAY($N$2),_xlfn.RANDARRAY(ROWS(_xlfn.ANCHORARRAY($N$2)),1,1,ROWS(_xlfn.ANCHORARRAY($N$2)),TRUE)) )} -> 2.4827178
A22: Lost | B22: 40 | C22: =_xlfn.RANK.AVG(B22,$B$2:$B$145,1) -> 72.5 | E22: Bonus | M22: 50 | N22: 40 | P22: {=AVERAGE( INDEX(_xlfn.ANCHORARRAY($M$2),_xlfn.RANDARRAY(ROWS(_xlfn.ANCHORARRAY($M$2)),1,1,ROWS(_xlfn.ANCHORARRAY($M$2)),TRUE)) ) - AVERAGE( INDEX(_xlfn.ANCHORARRAY($N$2),_xlfn.RANDARRAY(ROWS(_xlfn.ANCHORARRAY($N$2)),1,1,ROWS(_xlfn.ANCHORARRAY($N$2)),TRUE)) )} -> -1.7143986
A23: Lost | B23: 40 | C23: =_xlfn.RANK.AVG(B23,$B$2:$B$145,1) -> 72.5 | E23: two-sided p-value | F23: =2*(1-_xlfn.NORM.S.DIST(ABS(F19),TRUE)) -> 0.65103104 | G23: Trả lời một câu khác: Won và Lost có khác nhau theo bất kỳ hướng nào hay không? | M23: 10 | N23: 40 | P23: {=AVERAGE( INDEX(_xlfn.ANCHORARRAY($M$2),_xlfn.RANDARRAY(ROWS(_xlfn.ANCHORARRAY($M$2)),1,1,ROWS(_xlfn.ANCHORARRAY($M$2)),TRUE)) ) - AVERAGE( INDEX(_xlfn.ANCHORARRAY($N$2),_xlfn.RANDARRAY(ROWS(_xlfn.ANCHORARRAY($N$2)),1,1,ROWS(_xlfn.ANCHORARRAY($N$2)),TRUE)) )} -> -4.3393245
A24: Lost | B24: 20 | C24: =_xlfn.RANK.AVG(B24,$B$2:$B$145,1) -> 20.5 | E24: Effect Size | M24: 60 | N24: 20 | P24: {=AVERAGE( INDEX(_xlfn.ANCHORARRAY($M$2),_xlfn.RANDARRAY(ROWS(_xlfn.ANCHORARRAY($M$2)),1,1,ROWS(_xlfn.ANCHORARRAY($M$2)),TRUE)) ) - AVERAGE( INDEX(_xlfn.ANCHORARRAY($N$2),_xlfn.RANDARRAY(ROWS(_xlfn.ANCHORARRAY($N$2)),1,1,ROWS(_xlfn.ANCHORARRAY($N$2)),TRUE)) )} -> 6.3085127
A25: Lost | B25: 70 | C25: =_xlfn.RANK.AVG(B25,$B$2:$B$145,1) -> 127 | E25: Probability of Superiority | F25: =F14/(F2*F3) -> 0.52192376 | G25: Ý nghĩa: Nếu lấy ngẫu nhiên một Won opportunity và một Lost opportunity, Probability chỉ có khoảng 52.2% khả năng xếp Won cao hơn Lost, với ties được xử lý theo Mann–Whitney. | M25: 40 | N25: 70 | P25: {=AVERAGE( INDEX(_xlfn.ANCHORARRAY($M$2),_xlfn.RANDARRAY(ROWS(_xlfn.ANCHORARRAY($M$2)),1,1,ROWS(_xlfn.ANCHORARRAY($M$2)),TRUE)) ) - AVERAGE( INDEX(_xlfn.ANCHORARRAY($N$2),_xlfn.RANDARRAY(ROWS(_xlfn.ANCHORARRAY($N$2)),1,1,ROWS(_xlfn.ANCHORARRAY($N$2)),TRUE)) )} -> -2.0304167
A26: Lost | B26: 60 | C26: =_xlfn.RANK.AVG(B26,$B$2:$B$145,1) -> 114 | E26: Rank-biserial correlation | F26: =2*F25-1 -> 0.043847521 | G26: Đây là lý do tại sao không nên viết đơn giản: p > 0.05 nên không có effect. | I26: Hai evidence song song: p-value ≈ 0.326 + effect size ≈ 0.044 Cả hai đều cho thấy signal hiện tại yếu. | M26: 100 | N26: 60 | P26: {=AVERAGE( INDEX(_xlfn.ANCHORARRAY($M$2),_xlfn.RANDARRAY(ROWS(_xlfn.ANCHORARRAY($M$2)),1,1,ROWS(_xlfn.ANCHORARRAY($M$2)),TRUE)) ) - AVERAGE( INDEX(_xlfn.ANCHORARRAY($N$2),_xlfn.RANDARRAY(ROWS(_xlfn.ANCHORARRAY($N$2)),1,1,ROWS(_xlfn.ANCHORARRAY($N$2)),TRUE)) )} -> 0.83744815
A27: Lost | B27: 30 | C27: =_xlfn.RANK.AVG(B27,$B$2:$B$145,1) -> 46 | E27: Confidence Interval | G27: Mann–Whitney và difference in mean là hai statistic khác nhau. Vì vậy bổ sung: 95% CI for Mean Difference như một supporting statistic. | M27: 20 | N27: 30 | P27: {=AVERAGE( INDEX(_xlfn.ANCHORARRAY($M$2),_xlfn.RANDARRAY(ROWS(_xlfn.ANCHORARRAY($M$2)),1,1,ROWS(_xlfn.ANCHORARRAY($M$2)),TRUE)) ) - AVERAGE( INDEX(_xlfn.ANCHORARRAY($N$2),_xlfn.RANDARRAY(ROWS(_xlfn.ANCHORARRAY($N$2)),1,1,ROWS(_xlfn.ANCHORARRAY($N$2)),TRUE)) )} -> 1.9790638
A28: Lost | B28: 90 | C28: =_xlfn.RANK.AVG(B28,$B$2:$B$145,1) -> 138.5 | E28: Standard Error | F28: =SQRT(F8^2/F2+F9^2/F3) -> 3.6157036 | G28: chú ý: 0 nằm trong confidence interval nên dữ liệu hiện tại vẫn tương thích với: Won thấp hơn Lost một chút HOẶC Won cao hơn Lost một chút Chưa có estimate đủ precise. | M28: 40 | N28: 90 | P28: {=AVERAGE( INDEX(_xlfn.ANCHORARRAY($M$2),_xlfn.RANDARRAY(ROWS(_xlfn.ANCHORARRAY($M$2)),1,1,ROWS(_xlfn.ANCHORARRAY($M$2)),TRUE)) ) - AVERAGE( INDEX(_xlfn.ANCHORARRAY($N$2),_xlfn.RANDARRAY(ROWS(_xlfn.ANCHORARRAY($N$2)),1,1,ROWS(_xlfn.ANCHORARRAY($N$2)),TRUE)) )} -> -1.5386135
A29: Lost | B29: 60 | C29: =_xlfn.RANK.AVG(B29,$B$2:$B$145,1) -> 114 | E29: Welch degrees of freedom | F29: =((F8^2/F2+F9^2/F3)^2)/ ( ((F8^2/F2)^2/(F2-1)) + ((F9^2/F3)^2/(F3-1)) ) -> 132.12633 | M29: 80 | N29: 60 | P29: {=AVERAGE( INDEX(_xlfn.ANCHORARRAY($M$2),_xlfn.RANDARRAY(ROWS(_xlfn.ANCHORARRAY($M$2)),1,1,ROWS(_xlfn.ANCHORARRAY($M$2)),TRUE)) ) - AVERAGE( INDEX(_xlfn.ANCHORARRAY($N$2),_xlfn.RANDARRAY(ROWS(_xlfn.ANCHORARRAY($N$2)),1,1,ROWS(_xlfn.ANCHORARRAY($N$2)),TRUE)) )} -> 3.6717361
A30: Lost | B30: 70 | C30: =_xlfn.RANK.AVG(B30,$B$2:$B$145,1) -> 127 | E30: Critical t | F30: =_xlfn.T.INV.2T(0.05,F29) -> 1.9780988 | M30: 40 | N30: 70 | P30: {=AVERAGE( INDEX(_xlfn.ANCHORARRAY($M$2),_xlfn.RANDARRAY(ROWS(_xlfn.ANCHORARRAY($M$2)),1,1,ROWS(_xlfn.ANCHORARRAY($M$2)),TRUE)) ) - AVERAGE( INDEX(_xlfn.ANCHORARRAY($N$2),_xlfn.RANDARRAY(ROWS(_xlfn.ANCHORARRAY($N$2)),1,1,ROWS(_xlfn.ANCHORARRAY($N$2)),TRUE)) )} -> -6.7509382
A31: Lost | B31: 40 | C31: =_xlfn.RANK.AVG(B31,$B$2:$B$145,1) -> 72.5 | E31: Lower Bound | F31: =F10-F30*F28 -> -5.5918793 | G31: Mean Difference: +1.56 percentage points 95% CI: approximately [-5.6, +8.7] | M31: 50 | N31: 40 | P31: {=AVERAGE( INDEX(_xlfn.ANCHORARRAY($M$2),_xlfn.RANDARRAY(ROWS(_xlfn.ANCHORARRAY($M$2)),1,1,ROWS(_xlfn.ANCHORARRAY($M$2)),TRUE)) ) - AVERAGE( INDEX(_xlfn.ANCHORARRAY($N$2),_xlfn.RANDARRAY(ROWS(_xlfn.ANCHORARRAY($N$2)),1,1,ROWS(_xlfn.ANCHORARRAY($N$2)),TRUE)) )} -> 3.4248469
A32: Lost | B32: 50 | C32: =_xlfn.RANK.AVG(B32,$B$2:$B$145,1) -> 96.5 | E32: Upper Bound | F32: =F10+F30*F28 -> 8.7125587 | M32: 40 | N32: 50 | P32: {=AVERAGE( INDEX(_xlfn.ANCHORARRAY($M$2),_xlfn.RANDARRAY(ROWS(_xlfn.ANCHORARRAY($M$2)),1,1,ROWS(_xlfn.ANCHORARRAY($M$2)),TRUE)) ) - AVERAGE( INDEX(_xlfn.ANCHORARRAY($N$2),_xlfn.RANDARRAY(ROWS(_xlfn.ANCHORARRAY($N$2)),1,1,ROWS(_xlfn.ANCHORARRAY($N$2)),TRUE)) )} -> 0.88090065
A33: Lost | B33: 20 | C33: =_xlfn.RANK.AVG(B33,$B$2:$B$145,1) -> 20.5 | M33: 60 | N33: 20 | P33: {=AVERAGE( INDEX(_xlfn.ANCHORARRAY($M$2),_xlfn.RANDARRAY(ROWS(_xlfn.ANCHORARRAY($M$2)),1,1,ROWS(_xlfn.ANCHORARRAY($M$2)),TRUE)) ) - AVERAGE( INDEX(_xlfn.ANCHORARRAY($N$2),_xlfn.RANDARRAY(ROWS(_xlfn.ANCHORARRAY($N$2)),1,1,ROWS(_xlfn.ANCHORARRAY($N$2)),TRUE)) )} -> -5.6073474
A34: Lost | B34: 50 | C34: =_xlfn.RANK.AVG(B34,$B$2:$B$145,1) -> 96.5 | M34: 30 | N34: 50 | P34: {=AVERAGE( INDEX(_xlfn.ANCHORARRAY($M$2),_xlfn.RANDARRAY(ROWS(_xlfn.ANCHORARRAY($M$2)),1,1,ROWS(_xlfn.ANCHORARRAY($M$2)),TRUE)) ) - AVERAGE( INDEX(_xlfn.ANCHORARRAY($N$2),_xlfn.RANDARRAY(ROWS(_xlfn.ANCHORARRAY($N$2)),1,1,ROWS(_xlfn.ANCHORARRAY($N$2)),TRUE)) )} -> -4.3215485
A35: Lost | B35: 20 | C35: =_xlfn.RANK.AVG(B35,$B$2:$B$145,1) -> 20.5 | M35: 40 | N35: 20 | P35: {=AVERAGE( INDEX(_xlfn.ANCHORARRAY($M$2),_xlfn.RANDARRAY(ROWS(_xlfn.ANCHORARRAY($M$2)),1,1,ROWS(_xlfn.ANCHORARRAY($M$2)),TRUE)) ) - AVERAGE( INDEX(_xlfn.ANCHORARRAY($N$2),_xlfn.RANDARRAY(ROWS(_xlfn.ANCHORARRAY($N$2)),1,1,ROWS(_xlfn.ANCHORARRAY($N$2)),TRUE)) )} -> 4.6770689
A36: Lost | B36: 40 | C36: =_xlfn.RANK.AVG(B36,$B$2:$B$145,1) -> 72.5 | E36: Insight | M36: 80 | N36: 40 | P36: {=AVERAGE( INDEX(_xlfn.ANCHORARRAY($M$2),_xlfn.RANDARRAY(ROWS(_xlfn.ANCHORARRAY($M$2)),1,1,ROWS(_xlfn.ANCHORARRAY($M$2)),TRUE)) ) - AVERAGE( INDEX(_xlfn.ANCHORARRAY($N$2),_xlfn.RANDARRAY(ROWS(_xlfn.ANCHORARRAY($N$2)),1,1,ROWS(_xlfn.ANCHORARRAY($N$2)),TRUE)) )} -> 5.0069129
A37: Lost | B37: 50 | C37: =_xlfn.RANK.AVG(B37,$B$2:$B$145,1) -> 96.5 | E37: Mô tả: | M37: 30 | N37: 50 | P37: {=AVERAGE( INDEX(_xlfn.ANCHORARRAY($M$2),_xlfn.RANDARRAY(ROWS(_xlfn.ANCHORARRAY($M$2)),1,1,ROWS(_xlfn.ANCHORARRAY($M$2)),TRUE)) ) - AVERAGE( INDEX(_xlfn.ANCHORARRAY($N$2),_xlfn.RANDARRAY(ROWS(_xlfn.ANCHORARRAY($N$2)),1,1,ROWS(_xlfn.ANCHORARRAY($N$2)),TRUE)) )} -> 2.2299032
A38: Lost | B38: 50 | C38: =_xlfn.RANK.AVG(B38,$B$2:$B$145,1) -> 96.5 | M38: 40 | N38: 50 | P38: {=AVERAGE( INDEX(_xlfn.ANCHORARRAY($M$2),_xlfn.RANDARRAY(ROWS(_xlfn.ANCHORARRAY($M$2)),1,1,ROWS(_xlfn.ANCHORARRAY($M$2)),TRUE)) ) - AVERAGE( INDEX(_xlfn.ANCHORARRAY($N$2),_xlfn.RANDARRAY(ROWS(_xlfn.ANCHORARRAY($N$2)),1,1,ROWS(_xlfn.ANCHORARRAY($N$2)),TRUE)) )} -> 3.8929488
A39: Lost | B39: 40 | C39: =_xlfn.RANK.AVG(B39,$B$2:$B$145,1) -> 72.5 | E39: Won mean = 43.86% | M39: 60 | N39: 40 | P39: {=AVERAGE( INDEX(_xlfn.ANCHORARRAY($M$2),_xlfn.RANDARRAY(ROWS(_xlfn.ANCHORARRAY($M$2)),1,1,ROWS(_xlfn.ANCHORARRAY($M$2)),TRUE)) ) - AVERAGE( INDEX(_xlfn.ANCHORARRAY($N$2),_xlfn.RANDARRAY(ROWS(_xlfn.ANCHORARRAY($N$2)),1,1,ROWS(_xlfn.ANCHORARRAY($N$2)),TRUE)) )} -> -3.2925143
A40: Lost | B40: 100 | C40: =_xlfn.RANK.AVG(B40,$B$2:$B$145,1) -> 143.5 | E40: Lost mean = 42.30% | M40: 10 | N40: 100 | P40: {=AVERAGE( INDEX(_xlfn.ANCHORARRAY($M$2),_xlfn.RANDARRAY(ROWS(_xlfn.ANCHORARRAY($M$2)),1,1,ROWS(_xlfn.ANCHORARRAY($M$2)),TRUE)) ) - AVERAGE( INDEX(_xlfn.ANCHORARRAY($N$2),_xlfn.RANDARRAY(ROWS(_xlfn.ANCHORARRAY($N$2)),1,1,ROWS(_xlfn.ANCHORARRAY($N$2)),TRUE)) )} -> -4.2148924
A41: Lost | B41: 40 | C41: =_xlfn.RANK.AVG(B41,$B$2:$B$145,1) -> 72.5 | E41: Difference = +1.56 pp | M41: 90 | N41: 40 | P41: {=AVERAGE( INDEX(_xlfn.ANCHORARRAY($M$2),_xlfn.RANDARRAY(ROWS(_xlfn.ANCHORARRAY($M$2)),1,1,ROWS(_xlfn.ANCHORARRAY($M$2)),TRUE)) ) - AVERAGE( INDEX(_xlfn.ANCHORARRAY($N$2),_xlfn.RANDARRAY(ROWS(_xlfn.ANCHORARRAY($N$2)),1,1,ROWS(_xlfn.ANCHORARRAY($N$2)),TRUE)) )} -> -0.17973533
A42: Lost | B42: 70 | C42: =_xlfn.RANK.AVG(B42,$B$2:$B$145,1) -> 127 | M42: 30 | N42: 70 | P42: {=AVERAGE( INDEX(_xlfn.ANCHORARRAY($M$2),_xlfn.RANDARRAY(ROWS(_xlfn.ANCHORARRAY($M$2)),1,1,ROWS(_xlfn.ANCHORARRAY($M$2)),TRUE)) ) - AVERAGE( INDEX(_xlfn.ANCHORARRAY($N$2),_xlfn.RANDARRAY(ROWS(_xlfn.ANCHORARRAY($N$2)),1,1,ROWS(_xlfn.ANCHORARRAY($N$2)),TRUE)) )} -> 1.4201067
A43: Lost | B43: 30 | C43: =_xlfn.RANK.AVG(B43,$B$2:$B$145,1) -> 46 | E43: ↓ | M43: 40 | N43: 30 | P43: {=AVERAGE( INDEX(_xlfn.ANCHORARRAY($M$2),_xlfn.RANDARRAY(ROWS(_xlfn.ANCHORARRAY($M$2)),1,1,ROWS(_xlfn.ANCHORARRAY($M$2)),TRUE)) ) - AVERAGE( INDEX(_xlfn.ANCHORARRAY($N$2),_xlfn.RANDARRAY(ROWS(_xlfn.ANCHORARRAY($N$2)),1,1,ROWS(_xlfn.ANCHORARRAY($N$2)),TRUE)) )} -> 2.9251432
A44: Lost | B44: 70 | C44: =_xlfn.RANK.AVG(B44,$B$2:$B$145,1) -> 127 | M44: 60 | N44: 70 | P44: {=AVERAGE( INDEX(_xlfn.ANCHORARRAY($M$2),_xlfn.RANDARRAY(ROWS(_xlfn.ANCHORARRAY($M$2)),1,1,ROWS(_xlfn.ANCHORARRAY($M$2)),TRUE)) ) - AVERAGE( INDEX(_xlfn.ANCHORARRAY($N$2),_xlfn.RANDARRAY(ROWS(_xlfn.ANCHORARRAY($N$2)),1,1,ROWS(_xlfn.ANCHORARRAY($N$2)),TRUE)) )} -> 4.8469287
A45: Lost | B45: 30 | C45: =_xlfn.RANK.AVG(B45,$B$2:$B$145,1) -> 46 | E45: Bằng chứng thống kê: | M45: 20 | N45: 30 | P45: {=AVERAGE( INDEX(_xlfn.ANCHORARRAY($M$2),_xlfn.RANDARRAY(ROWS(_xlfn.ANCHORARRAY($M$2)),1,1,ROWS(_xlfn.ANCHORARRAY($M$2)),TRUE)) ) - AVERAGE( INDEX(_xlfn.ANCHORARRAY($N$2),_xlfn.RANDARRAY(ROWS(_xlfn.ANCHORARRAY($N$2)),1,1,ROWS(_xlfn.ANCHORARRAY($N$2)),TRUE)) )} -> 3.2628876
A46: Lost | B46: 90 | C46: =_xlfn.RANK.AVG(B46,$B$2:$B$145,1) -> 138.5 | M46: 50 | N46: 90 | P46: {=AVERAGE( INDEX(_xlfn.ANCHORARRAY($M$2),_xlfn.RANDARRAY(ROWS(_xlfn.ANCHORARRAY($M$2)),1,1,ROWS(_xlfn.ANCHORARRAY($M$2)),TRUE)) ) - AVERAGE( INDEX(_xlfn.ANCHORARRAY($N$2),_xlfn.RANDARRAY(ROWS(_xlfn.ANCHORARRAY($N$2)),1,1,ROWS(_xlfn.ANCHORARRAY($N$2)),TRUE)) )} -> 1.6669959
A47: Lost | B47: 30 | C47: =_xlfn.RANK.AVG(B47,$B$2:$B$145,1) -> 46 | E47: Mann–Whitney | M47: 50 | N47: 30 | P47: {=AVERAGE( INDEX(_xlfn.ANCHORARRAY($M$2),_xlfn.RANDARRAY(ROWS(_xlfn.ANCHORARRAY($M$2)),1,1,ROWS(_xlfn.ANCHORARRAY($M$2)),TRUE)) ) - AVERAGE( INDEX(_xlfn.ANCHORARRAY($N$2),_xlfn.RANDARRAY(ROWS(_xlfn.ANCHORARRAY($N$2)),1,1,ROWS(_xlfn.ANCHORARRAY($N$2)),TRUE)) )} -> 0.93817895
A48: Lost | B48: 40 | C48: =_xlfn.RANK.AVG(B48,$B$2:$B$145,1) -> 72.5 | E48: p = 0.326 > 0.05 | M48: 20 | N48: 40 | P48: {=AVERAGE( INDEX(_xlfn.ANCHORARRAY($M$2),_xlfn.RANDARRAY(ROWS(_xlfn.ANCHORARRAY($M$2)),1,1,ROWS(_xlfn.ANCHORARRAY($M$2)),TRUE)) ) - AVERAGE( INDEX(_xlfn.ANCHORARRAY($N$2),_xlfn.RANDARRAY(ROWS(_xlfn.ANCHORARRAY($N$2)),1,1,ROWS(_xlfn.ANCHORARRAY($N$2)),TRUE)) )} -> 0.91842781
A49: Lost | B49: 70 | C49: =_xlfn.RANK.AVG(B49,$B$2:$B$145,1) -> 127 | M49: 70 | N49: 70 | P49: {=AVERAGE( INDEX(_xlfn.ANCHORARRAY($M$2),_xlfn.RANDARRAY(ROWS(_xlfn.ANCHORARRAY($M$2)),1,1,ROWS(_xlfn.ANCHORARRAY($M$2)),TRUE)) ) - AVERAGE( INDEX(_xlfn.ANCHORARRAY($N$2),_xlfn.RANDARRAY(ROWS(_xlfn.ANCHORARRAY($N$2)),1,1,ROWS(_xlfn.ANCHORARRAY($N$2)),TRUE)) )} -> 4.5091843
A50: Lost | B50: 80 | C50: =_xlfn.RANK.AVG(B50,$B$2:$B$145,1) -> 133 | E50: ↓ | M50: 40 | N50: 80 | P50: {=AVERAGE( INDEX(_xlfn.ANCHORARRAY($M$2),_xlfn.RANDARRAY(ROWS(_xlfn.ANCHORARRAY($M$2)),1,1,ROWS(_xlfn.ANCHORARRAY($M$2)),TRUE)) ) - AVERAGE( INDEX(_xlfn.ANCHORARRAY($N$2),_xlfn.RANDARRAY(ROWS(_xlfn.ANCHORARRAY($N$2)),1,1,ROWS(_xlfn.ANCHORARRAY($N$2)),TRUE)) )} -> 0.53525578
A51: Lost | B51: 10 | C51: =_xlfn.RANK.AVG(B51,$B$2:$B$145,1) -> 3.5 | M51: 90 | N51: 10 | P51: {=AVERAGE( INDEX(_xlfn.ANCHORARRAY($M$2),_xlfn.RANDARRAY(ROWS(_xlfn.ANCHORARRAY($M$2)),1,1,ROWS(_xlfn.ANCHORARRAY($M$2)),TRUE)) ) - AVERAGE( INDEX(_xlfn.ANCHORARRAY($N$2),_xlfn.RANDARRAY(ROWS(_xlfn.ANCHORARRAY($N$2)),1,1,ROWS(_xlfn.ANCHORARRAY($N$2)),TRUE)) )} -> 3.6243334
A52: Lost | B52: 20 | C52: =_xlfn.RANK.AVG(B52,$B$2:$B$145,1) -> 20.5 | E52: Kết quả: | M52: 70 | N52: 20 | P52: {=AVERAGE( INDEX(_xlfn.ANCHORARRAY($M$2),_xlfn.RANDARRAY(ROWS(_xlfn.ANCHORARRAY($M$2)),1,1,ROWS(_xlfn.ANCHORARRAY($M$2)),TRUE)) ) - AVERAGE( INDEX(_xlfn.ANCHORARRAY($N$2),_xlfn.RANDARRAY(ROWS(_xlfn.ANCHORARRAY($N$2)),1,1,ROWS(_xlfn.ANCHORARRAY($N$2)),TRUE)) )} -> -1.9158602
A53: Lost | B53: 30 | C53: =_xlfn.RANK.AVG(B53,$B$2:$B$145,1) -> 46 | M53: 20 | N53: 30 | P53: {=AVERAGE( INDEX(_xlfn.ANCHORARRAY($M$2),_xlfn.RANDARRAY(ROWS(_xlfn.ANCHORARRAY($M$2)),1,1,ROWS(_xlfn.ANCHORARRAY($M$2)),TRUE)) ) - AVERAGE( INDEX(_xlfn.ANCHORARRAY($N$2),_xlfn.RANDARRAY(ROWS(_xlfn.ANCHORARRAY($N$2)),1,1,ROWS(_xlfn.ANCHORARRAY($N$2)),TRUE)) )} -> 2.3839621
A54: Lost | B54: 20 | C54: =_xlfn.RANK.AVG(B54,$B$2:$B$145,1) -> 20.5 | E54: Rank-biserial ≈ 0.044 | M54: 40 | N54: 20 | P54: {=AVERAGE( INDEX(_xlfn.ANCHORARRAY($M$2),_xlfn.RANDARRAY(ROWS(_xlfn.ANCHORARRAY($M$2)),1,1,ROWS(_xlfn.ANCHORARRAY($M$2)),TRUE)) ) - AVERAGE( INDEX(_xlfn.ANCHORARRAY($N$2),_xlfn.RANDARRAY(ROWS(_xlfn.ANCHORARRAY($N$2)),1,1,ROWS(_xlfn.ANCHORARRAY($N$2)),TRUE)) )} -> -0.45427612
A55: Lost | B55: 30 | C55: =_xlfn.RANK.AVG(B55,$B$2:$B$145,1) -> 46 | E55: Probability of superiority ≈ 52.2% | M55: 30 | N55: 30 | P55: {=AVERAGE( INDEX(_xlfn.ANCHORARRAY($M$2),_xlfn.RANDARRAY(ROWS(_xlfn.ANCHORARRAY($M$2)),1,1,ROWS(_xlfn.ANCHORARRAY($M$2)),TRUE)) ) - AVERAGE( INDEX(_xlfn.ANCHORARRAY($N$2),_xlfn.RANDARRAY(ROWS(_xlfn.ANCHORARRAY($N$2)),1,1,ROWS(_xlfn.ANCHORARRAY($N$2)),TRUE)) )} -> 8.7576536
A56: Lost | B56: 30 | C56: =_xlfn.RANK.AVG(B56,$B$2:$B$145,1) -> 46 | M56: 50 | N56: 30 | P56: {=AVERAGE( INDEX(_xlfn.ANCHORARRAY($M$2),_xlfn.RANDARRAY(ROWS(_xlfn.ANCHORARRAY($M$2)),1,1,ROWS(_xlfn.ANCHORARRAY($M$2)),TRUE)) ) - AVERAGE( INDEX(_xlfn.ANCHORARRAY($N$2),_xlfn.RANDARRAY(ROWS(_xlfn.ANCHORARRAY($N$2)),1,1,ROWS(_xlfn.ANCHORARRAY($N$2)),TRUE)) )} -> 4.2148924
A57: Lost | B57: 60 | C57: =_xlfn.RANK.AVG(B57,$B$2:$B$145,1) -> 114 | E57: ↓ | M57: 40 | N57: 60 | P57: {=AVERAGE( INDEX(_xlfn.ANCHORARRAY($M$2),_xlfn.RANDARRAY(ROWS(_xlfn.ANCHORARRAY($M$2)),1,1,ROWS(_xlfn.ANCHORARRAY($M$2)),TRUE)) ) - AVERAGE( INDEX(_xlfn.ANCHORARRAY($N$2),_xlfn.RANDARRAY(ROWS(_xlfn.ANCHORARRAY($N$2)),1,1,ROWS(_xlfn.ANCHORARRAY($N$2)),TRUE)) )} -> -4.730397
A58: Lost | B58: 20 | C58: =_xlfn.RANK.AVG(B58,$B$2:$B$145,1) -> 20.5 | M58: 30 | N58: 20 | P58: {=AVERAGE( INDEX(_xlfn.ANCHORARRAY($M$2),_xlfn.RANDARRAY(ROWS(_xlfn.ANCHORARRAY($M$2)),1,1,ROWS(_xlfn.ANCHORARRAY($M$2)),TRUE)) ) - AVERAGE( INDEX(_xlfn.ANCHORARRAY($N$2),_xlfn.RANDARRAY(ROWS(_xlfn.ANCHORARRAY($N$2)),1,1,ROWS(_xlfn.ANCHORARRAY($N$2)),TRUE)) )} -> -1.7894529
A59: Lost | B59: 10 | C59: =_xlfn.RANK.AVG(B59,$B$2:$B$145,1) -> 3.5 | E59: Độ biến thiên: | M59: 50 | N59: 10 | P59: {=AVERAGE( INDEX(_xlfn.ANCHORARRAY($M$2),_xlfn.RANDARRAY(ROWS(_xlfn.ANCHORARRAY($M$2)),1,1,ROWS(_xlfn.ANCHORARRAY($M$2)),TRUE)) ) - AVERAGE( INDEX(_xlfn.ANCHORARRAY($N$2),_xlfn.RANDARRAY(ROWS(_xlfn.ANCHORARRAY($N$2)),1,1,ROWS(_xlfn.ANCHORARRAY($N$2)),TRUE)) )} -> 1.7578511
A60: Lost | B60: 50 | C60: =_xlfn.RANK.AVG(B60,$B$2:$B$145,1) -> 96.5 | M60: 70 | N60: 50 | P60: {=AVERAGE( INDEX(_xlfn.ANCHORARRAY($M$2),_xlfn.RANDARRAY(ROWS(_xlfn.ANCHORARRAY($M$2)),1,1,ROWS(_xlfn.ANCHORARRAY($M$2)),TRUE)) ) - AVERAGE( INDEX(_xlfn.ANCHORARRAY($N$2),_xlfn.RANDARRAY(ROWS(_xlfn.ANCHORARRAY($N$2)),1,1,ROWS(_xlfn.ANCHORARRAY($N$2)),TRUE)) )} -> 5.4690895
A61: Lost | B61: 90 | C61: =_xlfn.RANK.AVG(B61,$B$2:$B$145,1) -> 138.5 | E61: 95% CI of mean difference | M61: 60 | N61: 90 | P61: {=AVERAGE( INDEX(_xlfn.ANCHORARRAY($M$2),_xlfn.RANDARRAY(ROWS(_xlfn.ANCHORARRAY($M$2)),1,1,ROWS(_xlfn.ANCHORARRAY($M$2)),TRUE)) ) - AVERAGE( INDEX(_xlfn.ANCHORARRAY($N$2),_xlfn.RANDARRAY(ROWS(_xlfn.ANCHORARRAY($N$2)),1,1,ROWS(_xlfn.ANCHORARRAY($N$2)),TRUE)) )} -> 2.9962473
A62: Lost | B62: 40 | C62: =_xlfn.RANK.AVG(B62,$B$2:$B$145,1) -> 72.5 | E62: ≈ [-5.6, +8.7] pp | M62: 40 | N62: 40 | P62: {=AVERAGE( INDEX(_xlfn.ANCHORARRAY($M$2),_xlfn.RANDARRAY(ROWS(_xlfn.ANCHORARRAY($M$2)),1,1,ROWS(_xlfn.ANCHORARRAY($M$2)),TRUE)) ) - AVERAGE( INDEX(_xlfn.ANCHORARRAY($N$2),_xlfn.RANDARRAY(ROWS(_xlfn.ANCHORARRAY($N$2)),1,1,ROWS(_xlfn.ANCHORARRAY($N$2)),TRUE)) )} -> 4.9693857
A63: Won | B63: 20 | C63: =_xlfn.RANK.AVG(B63,$B$2:$B$145,1) -> 20.5 | M63: 20 | P63: {=AVERAGE( INDEX(_xlfn.ANCHORARRAY($M$2),_xlfn.RANDARRAY(ROWS(_xlfn.ANCHORARRAY($M$2)),1,1,ROWS(_xlfn.ANCHORARRAY($M$2)),TRUE)) ) - AVERAGE( INDEX(_xlfn.ANCHORARRAY($N$2),_xlfn.RANDARRAY(ROWS(_xlfn.ANCHORARRAY($N$2)),1,1,ROWS(_xlfn.ANCHORARRAY($N$2)),TRUE)) )} -> 1.617618
A64: Won | B64: 20 | C64: =_xlfn.RANK.AVG(B64,$B$2:$B$145,1) -> 20.5 | E64: ↓ | M64: 60 | P64: {=AVERAGE( INDEX(_xlfn.ANCHORARRAY($M$2),_xlfn.RANDARRAY(ROWS(_xlfn.ANCHORARRAY($M$2)),1,1,ROWS(_xlfn.ANCHORARRAY($M$2)),TRUE)) ) - AVERAGE( INDEX(_xlfn.ANCHORARRAY($N$2),_xlfn.RANDARRAY(ROWS(_xlfn.ANCHORARRAY($N$2)),1,1,ROWS(_xlfn.ANCHORARRAY($N$2)),TRUE)) )} -> 2.7414576
A65: Won | B65: 20 | C65: =_xlfn.RANK.AVG(B65,$B$2:$B$145,1) -> 20.5 | M65: 20 | P65: {=AVERAGE( INDEX(_xlfn.ANCHORARRAY($M$2),_xlfn.RANDARRAY(ROWS(_xlfn.ANCHORARRAY($M$2)),1,1,ROWS(_xlfn.ANCHORARRAY($M$2)),TRUE)) ) - AVERAGE( INDEX(_xlfn.ANCHORARRAY($N$2),_xlfn.RANDARRAY(ROWS(_xlfn.ANCHORARRAY($N$2)),1,1,ROWS(_xlfn.ANCHORARRAY($N$2)),TRUE)) )} -> 0.9026269
A66: Won | B66: 40 | C66: =_xlfn.RANK.AVG(B66,$B$2:$B$145,1) -> 72.5 | E66: Conclusion | M66: 30 | P66: {=AVERAGE( INDEX(_xlfn.ANCHORARRAY($M$2),_xlfn.RANDARRAY(ROWS(_xlfn.ANCHORARRAY($M$2)),1,1,ROWS(_xlfn.ANCHORARRAY($M$2)),TRUE)) ) - AVERAGE( INDEX(_xlfn.ANCHORARRAY($N$2),_xlfn.RANDARRAY(ROWS(_xlfn.ANCHORARRAY($N$2)),1,1,ROWS(_xlfn.ANCHORARRAY($N$2)),TRUE)) )} -> -6.6679834
A67: Won | B67: 10 | C67: =_xlfn.RANK.AVG(B67,$B$2:$B$145,1) -> 3.5 | M67: 60 | P67: {=AVERAGE( INDEX(_xlfn.ANCHORARRAY($M$2),_xlfn.RANDARRAY(ROWS(_xlfn.ANCHORARRAY($M$2)),1,1,ROWS(_xlfn.ANCHORARRAY($M$2)),TRUE)) ) - AVERAGE( INDEX(_xlfn.ANCHORARRAY($N$2),_xlfn.RANDARRAY(ROWS(_xlfn.ANCHORARRAY($N$2)),1,1,ROWS(_xlfn.ANCHORARRAY($N$2)),TRUE)) )} -> -3.8060438
A68: Won | B68: 20 | C68: =_xlfn.RANK.AVG(B68,$B$2:$B$145,1) -> 20.5 | E68: Dữ liệu lịch sử không cung cấp đủ bằng chứng cho thấy các cơ hội Won có probability cao hơn một cách có hệ thống so với các cơ hội Lost. | M68: 30 | P68: {=AVERAGE( INDEX(_xlfn.ANCHORARRAY($M$2),_xlfn.RANDARRAY(ROWS(_xlfn.ANCHORARRAY($M$2)),1,1,ROWS(_xlfn.ANCHORARRAY($M$2)),TRUE)) ) - AVERAGE( INDEX(_xlfn.ANCHORARRAY($N$2),_xlfn.RANDARRAY(ROWS(_xlfn.ANCHORARRAY($N$2)),1,1,ROWS(_xlfn.ANCHORARRAY($N$2)),TRUE)) )} -> 4.0766344
A69: Won | B69: 20 | C69: =_xlfn.RANK.AVG(B69,$B$2:$B$145,1) -> 20.5 | M69: 60 | P69: {=AVERAGE( INDEX(_xlfn.ANCHORARRAY($M$2),_xlfn.RANDARRAY(ROWS(_xlfn.ANCHORARRAY($M$2)),1,1,ROWS(_xlfn.ANCHORARRAY($M$2)),TRUE)) ) - AVERAGE( INDEX(_xlfn.ANCHORARRAY($N$2),_xlfn.RANDARRAY(ROWS(_xlfn.ANCHORARRAY($N$2)),1,1,ROWS(_xlfn.ANCHORARRAY($N$2)),TRUE)) )} -> 1.5939167
A70: Won | B70: 60 | C70: =_xlfn.RANK.AVG(B70,$B$2:$B$145,1) -> 114 | E70: ↓ | M70: 30 | P70: {=AVERAGE( INDEX(_xlfn.ANCHORARRAY($M$2),_xlfn.RANDARRAY(ROWS(_xlfn.ANCHORARRAY($M$2)),1,1,ROWS(_xlfn.ANCHORARRAY($M$2)),TRUE)) ) - AVERAGE( INDEX(_xlfn.ANCHORARRAY($N$2),_xlfn.RANDARRAY(ROWS(_xlfn.ANCHORARRAY($N$2)),1,1,ROWS(_xlfn.ANCHORARRAY($N$2)),TRUE)) )} -> 1.686747
A71: Won | B71: 60 | C71: =_xlfn.RANK.AVG(B71,$B$2:$B$145,1) -> 114 | M71: 40 | P71: {=AVERAGE( INDEX(_xlfn.ANCHORARRAY($M$2),_xlfn.RANDARRAY(ROWS(_xlfn.ANCHORARRAY($M$2)),1,1,ROWS(_xlfn.ANCHORARRAY($M$2)),TRUE)) ) - AVERAGE( INDEX(_xlfn.ANCHORARRAY($N$2),_xlfn.RANDARRAY(ROWS(_xlfn.ANCHORARRAY($N$2)),1,1,ROWS(_xlfn.ANCHORARRAY($N$2)),TRUE)) )} -> -2.0600435
A72: Won | B72: 60 | C72: =_xlfn.RANK.AVG(B72,$B$2:$B$145,1) -> 114 | E72: Business interpretation | M72: 40 | P72: {=AVERAGE( INDEX(_xlfn.ANCHORARRAY($M$2),_xlfn.RANDARRAY(ROWS(_xlfn.ANCHORARRAY($M$2)),1,1,ROWS(_xlfn.ANCHORARRAY($M$2)),TRUE)) ) - AVERAGE( INDEX(_xlfn.ANCHORARRAY($N$2),_xlfn.RANDARRAY(ROWS(_xlfn.ANCHORARRAY($N$2)),1,1,ROWS(_xlfn.ANCHORARRAY($N$2)),TRUE)) )} -> 2.8816907
A73: Won | B73: 90 | C73: =_xlfn.RANK.AVG(B73,$B$2:$B$145,1) -> 138.5 | M73: 30 | P73: {=AVERAGE( INDEX(_xlfn.ANCHORARRAY($M$2),_xlfn.RANDARRAY(ROWS(_xlfn.ANCHORARRAY($M$2)),1,1,ROWS(_xlfn.ANCHORARRAY($M$2)),TRUE)) ) - AVERAGE( INDEX(_xlfn.ANCHORARRAY($N$2),_xlfn.RANDARRAY(ROWS(_xlfn.ANCHORARRAY($N$2)),1,1,ROWS(_xlfn.ANCHORARRAY($N$2)),TRUE)) )} -> 5.5224175
A74: Won | B74: 30 | C74: =_xlfn.RANK.AVG(B74,$B$2:$B$145,1) -> 46 | E74: Trường Probability có khả năng hạn chế trong việc phân biệt các cơ hội Won và Lost trong tương lai nếu chỉ dựa vào data này. | M74: 40 | P74: {=AVERAGE( INDEX(_xlfn.ANCHORARRAY($M$2),_xlfn.RANDARRAY(ROWS(_xlfn.ANCHORARRAY($M$2)),1,1,ROWS(_xlfn.ANCHORARRAY($M$2)),TRUE)) ) - AVERAGE( INDEX(_xlfn.ANCHORARRAY($N$2),_xlfn.RANDARRAY(ROWS(_xlfn.ANCHORARRAY($N$2)),1,1,ROWS(_xlfn.ANCHORARRAY($N$2)),TRUE)) )} -> -7.0195536
A75: Won | B75: 40 | C75: =_xlfn.RANK.AVG(B75,$B$2:$B$145,1) -> 72.5 | M75: 70 | P75: {=AVERAGE( INDEX(_xlfn.ANCHORARRAY($M$2),_xlfn.RANDARRAY(ROWS(_xlfn.ANCHORARRAY($M$2)),1,1,ROWS(_xlfn.ANCHORARRAY($M$2)),TRUE)) ) - AVERAGE( INDEX(_xlfn.ANCHORARRAY($N$2),_xlfn.RANDARRAY(ROWS(_xlfn.ANCHORARRAY($N$2)),1,1,ROWS(_xlfn.ANCHORARRAY($N$2)),TRUE)) )} -> 3.5413786
A76: Won | B76: 60 | C76: =_xlfn.RANK.AVG(B76,$B$2:$B$145,1) -> 114 | M76: 20 | P76: {=AVERAGE( INDEX(_xlfn.ANCHORARRAY($M$2),_xlfn.RANDARRAY(ROWS(_xlfn.ANCHORARRAY($M$2)),1,1,ROWS(_xlfn.ANCHORARRAY($M$2)),TRUE)) ) - AVERAGE( INDEX(_xlfn.ANCHORARRAY($N$2),_xlfn.RANDARRAY(ROWS(_xlfn.ANCHORARRAY($N$2)),1,1,ROWS(_xlfn.ANCHORARRAY($N$2)),TRUE)) )} -> 1.6097176
A77: Won | B77: 60 | C77: =_xlfn.RANK.AVG(B77,$B$2:$B$145,1) -> 114 | M77: 60 | P77: {=AVERAGE( INDEX(_xlfn.ANCHORARRAY($M$2),_xlfn.RANDARRAY(ROWS(_xlfn.ANCHORARRAY($M$2)),1,1,ROWS(_xlfn.ANCHORARRAY($M$2)),TRUE)) ) - AVERAGE( INDEX(_xlfn.ANCHORARRAY($N$2),_xlfn.RANDARRAY(ROWS(_xlfn.ANCHORARRAY($N$2)),1,1,ROWS(_xlfn.ANCHORARRAY($N$2)),TRUE)) )} -> -4.2109421
A78: Won | B78: 10 | C78: =_xlfn.RANK.AVG(B78,$B$2:$B$145,1) -> 3.5 | M78: 90 | P78: {=AVERAGE( INDEX(_xlfn.ANCHORARRAY($M$2),_xlfn.RANDARRAY(ROWS(_xlfn.ANCHORARRAY($M$2)),1,1,ROWS(_xlfn.ANCHORARRAY($M$2)),TRUE)) ) - AVERAGE( INDEX(_xlfn.ANCHORARRAY($N$2),_xlfn.RANDARRAY(ROWS(_xlfn.ANCHORARRAY($N$2)),1,1,ROWS(_xlfn.ANCHORARRAY($N$2)),TRUE)) )} -> 4.0193561
A79: Won | B79: 20 | C79: =_xlfn.RANK.AVG(B79,$B$2:$B$145,1) -> 20.5 | M79: 50 | P79: {=AVERAGE( INDEX(_xlfn.ANCHORARRAY($M$2),_xlfn.RANDARRAY(ROWS(_xlfn.ANCHORARRAY($M$2)),1,1,ROWS(_xlfn.ANCHORARRAY($M$2)),TRUE)) ) - AVERAGE( INDEX(_xlfn.ANCHORARRAY($N$2),_xlfn.RANDARRAY(ROWS(_xlfn.ANCHORARRAY($N$2)),1,1,ROWS(_xlfn.ANCHORARRAY($N$2)),TRUE)) )} -> -2.5281454
A80: Won | B80: 20 | C80: =_xlfn.RANK.AVG(B80,$B$2:$B$145,1) -> 20.5 | M80: 20 | P80: {=AVERAGE( INDEX(_xlfn.ANCHORARRAY($M$2),_xlfn.RANDARRAY(ROWS(_xlfn.ANCHORARRAY($M$2)),1,1,ROWS(_xlfn.ANCHORARRAY($M$2)),TRUE)) ) - AVERAGE( INDEX(_xlfn.ANCHORARRAY($N$2),_xlfn.RANDARRAY(ROWS(_xlfn.ANCHORARRAY($N$2)),1,1,ROWS(_xlfn.ANCHORARRAY($N$2)),TRUE)) )} -> 2.2062019
A81: Won | B81: 20 | C81: =_xlfn.RANK.AVG(B81,$B$2:$B$145,1) -> 20.5 | M81: 50 | P81: {=AVERAGE( INDEX(_xlfn.ANCHORARRAY($M$2),_xlfn.RANDARRAY(ROWS(_xlfn.ANCHORARRAY($M$2)),1,1,ROWS(_xlfn.ANCHORARRAY($M$2)),TRUE)) ) - AVERAGE( INDEX(_xlfn.ANCHORARRAY($N$2),_xlfn.RANDARRAY(ROWS(_xlfn.ANCHORARRAY($N$2)),1,1,ROWS(_xlfn.ANCHORARRAY($N$2)),TRUE)) )} -> -2.6288762
A82: Won | B82: 30 | C82: =_xlfn.RANK.AVG(B82,$B$2:$B$145,1) -> 46 | M82: 50 | P82: {=AVERAGE( INDEX(_xlfn.ANCHORARRAY($M$2),_xlfn.RANDARRAY(ROWS(_xlfn.ANCHORARRAY($M$2)),1,1,ROWS(_xlfn.ANCHORARRAY($M$2)),TRUE)) ) - AVERAGE( INDEX(_xlfn.ANCHORARRAY($N$2),_xlfn.RANDARRAY(ROWS(_xlfn.ANCHORARRAY($N$2)),1,1,ROWS(_xlfn.ANCHORARRAY($N$2)),TRUE)) )} -> 0.76831918
A83: Won | B83: 50 | C83: =_xlfn.RANK.AVG(B83,$B$2:$B$145,1) -> 96.5 | M83: 90 | P83: {=AVERAGE( INDEX(_xlfn.ANCHORARRAY($M$2),_xlfn.RANDARRAY(ROWS(_xlfn.ANCHORARRAY($M$2)),1,1,ROWS(_xlfn.ANCHORARRAY($M$2)),TRUE)) ) - AVERAGE( INDEX(_xlfn.ANCHORARRAY($N$2),_xlfn.RANDARRAY(ROWS(_xlfn.ANCHORARRAY($N$2)),1,1,ROWS(_xlfn.ANCHORARRAY($N$2)),TRUE)) )} -> 7.1518862
A84: Won | B84: 10 | C84: =_xlfn.RANK.AVG(B84,$B$2:$B$145,1) -> 3.5 | M84: 30 | P84: {=AVERAGE( INDEX(_xlfn.ANCHORARRAY($M$2),_xlfn.RANDARRAY(ROWS(_xlfn.ANCHORARRAY($M$2)),1,1,ROWS(_xlfn.ANCHORARRAY($M$2)),TRUE)) ) - AVERAGE( INDEX(_xlfn.ANCHORARRAY($N$2),_xlfn.RANDARRAY(ROWS(_xlfn.ANCHORARRAY($N$2)),1,1,ROWS(_xlfn.ANCHORARRAY($N$2)),TRUE)) )} -> 5.0701165
A85: Won | B85: 60 | C85: =_xlfn.RANK.AVG(B85,$B$2:$B$145,1) -> 114 | P85: {=AVERAGE( INDEX(_xlfn.ANCHORARRAY($M$2),_xlfn.RANDARRAY(ROWS(_xlfn.ANCHORARRAY($M$2)),1,1,ROWS(_xlfn.ANCHORARRAY($M$2)),TRUE)) ) - AVERAGE( INDEX(_xlfn.ANCHORARRAY($N$2),_xlfn.RANDARRAY(ROWS(_xlfn.ANCHORARRAY($N$2)),1,1,ROWS(_xlfn.ANCHORARRAY($N$2)),TRUE)) )} -> -2.5715979
A86: Won | B86: 40 | C86: =_xlfn.RANK.AVG(B86,$B$2:$B$145,1) -> 72.5 | P86: {=AVERAGE( INDEX(_xlfn.ANCHORARRAY($M$2),_xlfn.RANDARRAY(ROWS(_xlfn.ANCHORARRAY($M$2)),1,1,ROWS(_xlfn.ANCHORARRAY($M$2)),TRUE)) ) - AVERAGE( INDEX(_xlfn.ANCHORARRAY($N$2),_xlfn.RANDARRAY(ROWS(_xlfn.ANCHORARRAY($N$2)),1,1,ROWS(_xlfn.ANCHORARRAY($N$2)),TRUE)) )} -> -3.1345052
A87: Won | B87: 100 | C87: =_xlfn.RANK.AVG(B87,$B$2:$B$145,1) -> 143.5 | P87: {=AVERAGE( INDEX(_xlfn.ANCHORARRAY($M$2),_xlfn.RANDARRAY(ROWS(_xlfn.ANCHORARRAY($M$2)),1,1,ROWS(_xlfn.ANCHORARRAY($M$2)),TRUE)) ) - AVERAGE( INDEX(_xlfn.ANCHORARRAY($N$2),_xlfn.RANDARRAY(ROWS(_xlfn.ANCHORARRAY($N$2)),1,1,ROWS(_xlfn.ANCHORARRAY($N$2)),TRUE)) )} -> 2.8184871
A88: Won | B88: 20 | C88: =_xlfn.RANK.AVG(B88,$B$2:$B$145,1) -> 20.5 | P88: {=AVERAGE( INDEX(_xlfn.ANCHORARRAY($M$2),_xlfn.RANDARRAY(ROWS(_xlfn.ANCHORARRAY($M$2)),1,1,ROWS(_xlfn.ANCHORARRAY($M$2)),TRUE)) ) - AVERAGE( INDEX(_xlfn.ANCHORARRAY($N$2),_xlfn.RANDARRAY(ROWS(_xlfn.ANCHORARRAY($N$2)),1,1,ROWS(_xlfn.ANCHORARRAY($N$2)),TRUE)) )} -> 2.3642109
A89: Won | B89: 40 | C89: =_xlfn.RANK.AVG(B89,$B$2:$B$145,1) -> 72.5 | P89: {=AVERAGE( INDEX(_xlfn.ANCHORARRAY($M$2),_xlfn.RANDARRAY(ROWS(_xlfn.ANCHORARRAY($M$2)),1,1,ROWS(_xlfn.ANCHORARRAY($M$2)),TRUE)) ) - AVERAGE( INDEX(_xlfn.ANCHORARRAY($N$2),_xlfn.RANDARRAY(ROWS(_xlfn.ANCHORARRAY($N$2)),1,1,ROWS(_xlfn.ANCHORARRAY($N$2)),TRUE)) )} -> 5.2913293
A90: Won | B90: 80 | C90: =_xlfn.RANK.AVG(B90,$B$2:$B$145,1) -> 133 | P90: {=AVERAGE( INDEX(_xlfn.ANCHORARRAY($M$2),_xlfn.RANDARRAY(ROWS(_xlfn.ANCHORARRAY($M$2)),1,1,ROWS(_xlfn.ANCHORARRAY($M$2)),TRUE)) ) - AVERAGE( INDEX(_xlfn.ANCHORARRAY($N$2),_xlfn.RANDARRAY(ROWS(_xlfn.ANCHORARRAY($N$2)),1,1,ROWS(_xlfn.ANCHORARRAY($N$2)),TRUE)) )} -> -0.52735532
A91: Won | B91: 40 | C91: =_xlfn.RANK.AVG(B91,$B$2:$B$145,1) -> 72.5 | P91: {=AVERAGE( INDEX(_xlfn.ANCHORARRAY($M$2),_xlfn.RANDARRAY(ROWS(_xlfn.ANCHORARRAY($M$2)),1,1,ROWS(_xlfn.ANCHORARRAY($M$2)),TRUE)) ) - AVERAGE( INDEX(_xlfn.ANCHORARRAY($N$2),_xlfn.RANDARRAY(ROWS(_xlfn.ANCHORARRAY($N$2)),1,1,ROWS(_xlfn.ANCHORARRAY($N$2)),TRUE)) )} -> 5.4216867
A92: Won | B92: 50 | C92: =_xlfn.RANK.AVG(B92,$B$2:$B$145,1) -> 96.5 | P92: {=AVERAGE( INDEX(_xlfn.ANCHORARRAY($M$2),_xlfn.RANDARRAY(ROWS(_xlfn.ANCHORARRAY($M$2)),1,1,ROWS(_xlfn.ANCHORARRAY($M$2)),TRUE)) ) - AVERAGE( INDEX(_xlfn.ANCHORARRAY($N$2),_xlfn.RANDARRAY(ROWS(_xlfn.ANCHORARRAY($N$2)),1,1,ROWS(_xlfn.ANCHORARRAY($N$2)),TRUE)) )} -> -1.2541971
A93: Won | B93: 40 | C93: =_xlfn.RANK.AVG(B93,$B$2:$B$145,1) -> 72.5 | P93: {=AVERAGE( INDEX(_xlfn.ANCHORARRAY($M$2),_xlfn.RANDARRAY(ROWS(_xlfn.ANCHORARRAY($M$2)),1,1,ROWS(_xlfn.ANCHORARRAY($M$2)),TRUE)) ) - AVERAGE( INDEX(_xlfn.ANCHORARRAY($N$2),_xlfn.RANDARRAY(ROWS(_xlfn.ANCHORARRAY($N$2)),1,1,ROWS(_xlfn.ANCHORARRAY($N$2)),TRUE)) )} -> 2.0955955
A94: Won | B94: 60 | C94: =_xlfn.RANK.AVG(B94,$B$2:$B$145,1) -> 114 | P94: {=AVERAGE( INDEX(_xlfn.ANCHORARRAY($M$2),_xlfn.RANDARRAY(ROWS(_xlfn.ANCHORARRAY($M$2)),1,1,ROWS(_xlfn.ANCHORARRAY($M$2)),TRUE)) ) - AVERAGE( INDEX(_xlfn.ANCHORARRAY($N$2),_xlfn.RANDARRAY(ROWS(_xlfn.ANCHORARRAY($N$2)),1,1,ROWS(_xlfn.ANCHORARRAY($N$2)),TRUE)) )} -> 8.8583844
A95: Won | B95: 30 | C95: =_xlfn.RANK.AVG(B95,$B$2:$B$145,1) -> 46 | P95: {=AVERAGE( INDEX(_xlfn.ANCHORARRAY($M$2),_xlfn.RANDARRAY(ROWS(_xlfn.ANCHORARRAY($M$2)),1,1,ROWS(_xlfn.ANCHORARRAY($M$2)),TRUE)) ) - AVERAGE( INDEX(_xlfn.ANCHORARRAY($N$2),_xlfn.RANDARRAY(ROWS(_xlfn.ANCHORARRAY($N$2)),1,1,ROWS(_xlfn.ANCHORARRAY($N$2)),TRUE)) )} -> -3.5887814
A96: Won | B96: 40 | C96: =_xlfn.RANK.AVG(B96,$B$2:$B$145,1) -> 72.5 | P96: {=AVERAGE( INDEX(_xlfn.ANCHORARRAY($M$2),_xlfn.RANDARRAY(ROWS(_xlfn.ANCHORARRAY($M$2)),1,1,ROWS(_xlfn.ANCHORARRAY($M$2)),TRUE)) ) - AVERAGE( INDEX(_xlfn.ANCHORARRAY($N$2),_xlfn.RANDARRAY(ROWS(_xlfn.ANCHORARRAY($N$2)),1,1,ROWS(_xlfn.ANCHORARRAY($N$2)),TRUE)) )} -> 3.2036342
... A145: Won | B145: 30 | C145: =_xlfn.RANK.AVG(B145,$B$2:$B$145,1) -> 46 | P145: {=AVERAGE( INDEX(_xlfn.ANCHORARRAY($M$2),_xlfn.RANDARRAY(ROWS(_xlfn.ANCHORARRAY($M$2)),1,1,ROWS(_xlfn.ANCHORARRAY($M$2)),TRUE)) ) - AVERAGE( INDEX(_xlfn.ANCHORARRAY($N$2),_xlfn.RANDARRAY(ROWS(_xlfn.ANCHORARRAY($N$2)),1,1,ROWS(_xlfn.ANCHORARRAY($N$2)),TRUE)) )} -> 6.713411
P146: {=AVERAGE( INDEX(_xlfn.ANCHORARRAY($M$2),_xlfn.RANDARRAY(ROWS(_xlfn.ANCHORARRAY($M$2)),1,1,ROWS(_xlfn.ANCHORARRAY($M$2)),TRUE)) ) - AVERAGE( INDEX(_xlfn.ANCHORARRAY($N$2),_xlfn.RANDARRAY(ROWS(_xlfn.ANCHORARRAY($N$2)),1,1,ROWS(_xlfn.ANCHORARRAY($N$2)),TRUE)) )} -> 6.174205
P147: {=AVERAGE( INDEX(_xlfn.ANCHORARRAY($M$2),_xlfn.RANDARRAY(ROWS(_xlfn.ANCHORARRAY($M$2)),1,1,ROWS(_xlfn.ANCHORARRAY($M$2)),TRUE)) ) - AVERAGE( INDEX(_xlfn.ANCHORARRAY($N$2),_xlfn.RANDARRAY(ROWS(_xlfn.ANCHORARRAY($N$2)),1,1,ROWS(_xlfn.ANCHORARRAY($N$2)),TRUE)) )} -> 3.5552044
P148: {=AVERAGE( INDEX(_xlfn.ANCHORARRAY($M$2),_xlfn.RANDARRAY(ROWS(_xlfn.ANCHORARRAY($M$2)),1,1,ROWS(_xlfn.ANCHORARRAY($M$2)),TRUE)) ) - AVERAGE( INDEX(_xlfn.ANCHORARRAY($N$2),_xlfn.RANDARRAY(ROWS(_xlfn.ANCHORARRAY($N$2)),1,1,ROWS(_xlfn.ANCHORARRAY($N$2)),TRUE)) )} -> 2.225953
...

Sheet Analysis 3 - Probability Calibr
A1: 1. Chuẩn bị dữ liệu | H1: 2. Calibration Table
A2: Stage | B2: CRM Probability | C2: Actual Outcome | D2: Predicted Probability | E2: CRM Squared Error | F2: Baseline Squared Error | H2: Predicted Probability | I2: Opportunities | J2: Won | K2: Lost | L2: Actual Win Rate | M2: Calibration Gap | N2: Abs Gap | O2: Perfect Calibration | Q2: CRM Brier Score
A3: ='Analysis 2 — Hypothesis Testing'!A2 -> Lost | B3: ='Analysis 2 — Hypothesis Testing'!B2 -> 30 | C3: =IF(A3="Won",1,0) -> 0 | D3: =B3/100 -> 0.3 | E3: =(D3-C3)^2 -> 0.09 | F3: =($Q$6-C3)^2 -> 0.33222415 | H3: 0.1 | I3: =COUNTIF($B$3:$B$146,H3*100) -> 6 | J3: =COUNTIFS($B$3:$B$146,H3*100,$A$3:$A$146,"Won") -> 4 | K3: =I3-J3 -> 2 | L3: =J3/I3 -> 0.66666667 | M3: =L3-H3 -> 0.56666667 | N3: =ABS(M3) -> 0.56666667 | O3: =H3 -> 0.1 | Q3: =AVERAGE(E3:E146) -> 0.30333333
A4: ='Analysis 2 — Hypothesis Testing'!A3 -> Lost | B4: ='Analysis 2 — Hypothesis Testing'!B3 -> 20 | C4: =IF(A4="Won",1,0) -> 0 | D4: =B4/100 -> 0.2 | E4: =(D4-C4)^2 -> 0.04 | F4: =($Q$6-C4)^2 -> 0.33222415 | H4: 0.2 | I4: =COUNTIF($B$3:$B$146,H4*100) -> 28 | J4: =COUNTIFS($B$3:$B$146,H4*100,$A$3:$A$146,"Won") -> 16 | K4: =I4-J4 -> 12 | L4: =J4/I4 -> 0.57142857 | M4: =L4-H4 -> 0.37142857 | N4: =ABS(M4) -> 0.37142857 | O4: =H4 -> 0.2
A5: ='Analysis 2 — Hypothesis Testing'!A4 -> Lost | B5: ='Analysis 2 — Hypothesis Testing'!B4 -> 50 | C5: =IF(A5="Won",1,0) -> 0 | D5: =B5/100 -> 0.5 | E5: =(D5-C5)^2 -> 0.25 | F5: =($Q$6-C5)^2 -> 0.33222415 | H5: 0.3 | I5: =COUNTIF($B$3:$B$146,H5*100) -> 23 | J5: =COUNTIFS($B$3:$B$146,H5*100,$A$3:$A$146,"Won") -> 12 | K5: =I5-J5 -> 11 | L5: =J5/I5 -> 0.52173913 | M5: =L5-H5 -> 0.22173913 | N5: =ABS(M5) -> 0.22173913 | O5: =H5 -> 0.3 | Q5: Overall Win Rate
A6: ='Analysis 2 — Hypothesis Testing'!A5 -> Lost | B6: ='Analysis 2 — Hypothesis Testing'!B5 -> 30 | C6: =IF(A6="Won",1,0) -> 0 | D6: =B6/100 -> 0.3 | E6: =(D6-C6)^2 -> 0.09 | F6: =($Q$6-C6)^2 -> 0.33222415 | H6: 0.4 | I6: =COUNTIF($B$3:$B$146,H6*100) -> 30 | J6: =COUNTIFS($B$3:$B$146,H6*100,$A$3:$A$146,"Won") -> 16 | K6: =I6-J6 -> 14 | L6: =J6/I6 -> 0.53333333 | M6: =L6-H6 -> 0.13333333 | N6: =ABS(M6) -> 0.13333333 | O6: =H6 -> 0.4 | Q6: =AVERAGE(C3:C146) -> 0.57638889
A7: ='Analysis 2 — Hypothesis Testing'!A6 -> Lost | B7: ='Analysis 2 — Hypothesis Testing'!B6 -> 50 | C7: =IF(A7="Won",1,0) -> 0 | D7: =B7/100 -> 0.5 | E7: =(D7-C7)^2 -> 0.25 | F7: =($Q$6-C7)^2 -> 0.33222415 | H7: 0.5 | I7: =COUNTIF($B$3:$B$146,H7*100) -> 18 | J7: =COUNTIFS($B$3:$B$146,H7*100,$A$3:$A$146,"Won") -> 9 | K7: =I7-J7 -> 9 | L7: =J7/I7 -> 0.5 | M7: =L7-H7 -> 0 | N7: =ABS(M7) -> 0 | O7: =H7 -> 0.5
A8: ='Analysis 2 — Hypothesis Testing'!A7 -> Lost | B8: ='Analysis 2 — Hypothesis Testing'!B7 -> 20 | C8: =IF(A8="Won",1,0) -> 0 | D8: =B8/100 -> 0.2 | E8: =(D8-C8)^2 -> 0.04 | F8: =($Q$6-C8)^2 -> 0.33222415 | H8: 0.6 | I8: =COUNTIF($B$3:$B$146,H8*100) -> 17 | J8: =COUNTIFS($B$3:$B$146,H8*100,$A$3:$A$146,"Won") -> 14 | K8: =I8-J8 -> 3 | L8: =J8/I8 -> 0.82352941 | M8: =L8-H8 -> 0.22352941 | N8: =ABS(M8) -> 0.22352941 | O8: =H8 -> 0.6 | Q8: Naive Baseline Brier
A9: ='Analysis 2 — Hypothesis Testing'!A8 -> Lost | B9: ='Analysis 2 — Hypothesis Testing'!B8 -> 30 | C9: =IF(A9="Won",1,0) -> 0 | D9: =B9/100 -> 0.3 | E9: =(D9-C9)^2 -> 0.09 | F9: =($Q$6-C9)^2 -> 0.33222415 | H9: 0.7 | I9: =COUNTIF($B$3:$B$146,H9*100) -> 9 | J9: =COUNTIFS($B$3:$B$146,H9*100,$A$3:$A$146,"Won") -> 4 | K9: =I9-J9 -> 5 | L9: =J9/I9 -> 0.44444444 | M9: =L9-H9 -> -0.25555556 | N9: =ABS(M9) -> 0.25555556 | O9: =H9 -> 0.7 | Q9: =AVERAGE(F3:F146) -> 0.24416474
A10: ='Analysis 2 — Hypothesis Testing'!A9 -> Lost | B10: ='Analysis 2 — Hypothesis Testing'!B9 -> 50 | C10: =IF(A10="Won",1,0) -> 0 | D10: =B10/100 -> 0.5 | E10: =(D10-C10)^2 -> 0.25 | F10: =($Q$6-C10)^2 -> 0.33222415 | H10: 0.8 | I10: =COUNTIF($B$3:$B$146,H10*100) -> 3 | J10: =COUNTIFS($B$3:$B$146,H10*100,$A$3:$A$146,"Won") -> 2 | K10: =I10-J10 -> 1 | L10: =J10/I10 -> 0.66666667 | M10: =L10-H10 -> -0.13333333 | N10: =ABS(M10) -> 0.13333333 | O10: =H10 -> 0.8
A11: ='Analysis 2 — Hypothesis Testing'!A10 -> Lost | B11: ='Analysis 2 — Hypothesis Testing'!B10 -> 20 | C11: =IF(A11="Won",1,0) -> 0 | D11: =B11/100 -> 0.2 | E11: =(D11-C11)^2 -> 0.04 | F11: =($Q$6-C11)^2 -> 0.33222415 | H11: 0.9 | I11: =COUNTIF($B$3:$B$146,H11*100) -> 8 | J11: =COUNTIFS($B$3:$B$146,H11*100,$A$3:$A$146,"Won") -> 5 | K11: =I11-J11 -> 3 | L11: =J11/I11 -> 0.625 | M11: =L11-H11 -> -0.275 | N11: =ABS(M11) -> 0.275 | O11: =H11 -> 0.9 | Q11: Vì Brier càng nhỏ càng tốt nên từ dữ liệu cho thấy CRM Probability thậm chí forecast outcome kém hơn một baseline rất đơn giản chỉ dự đoán 57.6% cho tất cả opportunity.
A12: ='Analysis 2 — Hypothesis Testing'!A11 -> Lost | B12: ='Analysis 2 — Hypothesis Testing'!B11 -> 20 | C12: =IF(A12="Won",1,0) -> 0 | D12: =B12/100 -> 0.2 | E12: =(D12-C12)^2 -> 0.04 | F12: =($Q$6-C12)^2 -> 0.33222415 | H12: 1 | I12: =COUNTIF($B$3:$B$146,H12*100) -> 2 | J12: =COUNTIFS($B$3:$B$146,H12*100,$A$3:$A$146,"Won") -> 1 | K12: =I12-J12 -> 1 | L12: =J12/I12 -> 0.5 | M12: =L12-H12 -> -0.5 | N12: =ABS(M12) -> 0.5 | O12: =H12 -> 1
A13: ='Analysis 2 — Hypothesis Testing'!A12 -> Lost | B13: ='Analysis 2 — Hypothesis Testing'!B12 -> 40 | C13: =IF(A13="Won",1,0) -> 0 | D13: =B13/100 -> 0.4 | E13: =(D13-C13)^2 -> 0.16 | F13: =($Q$6-C13)^2 -> 0.33222415 | Q13: Brier Skill Score
A14: ='Analysis 2 — Hypothesis Testing'!A13 -> Lost | B14: ='Analysis 2 — Hypothesis Testing'!B13 -> 20 | C14: =IF(A14="Won",1,0) -> 0 | D14: =B14/100 -> 0.2 | E14: =(D14-C14)^2 -> 0.04 | F14: =($Q$6-C14)^2 -> 0.33222415 | Q14: =1-Q3/Q9 -> -0.24233063
A15: ='Analysis 2 — Hypothesis Testing'!A14 -> Lost | B15: ='Analysis 2 — Hypothesis Testing'!B14 -> 40 | C15: =IF(A15="Won",1,0) -> 0 | D15: =B15/100 -> 0.4 | E15: =(D15-C15)^2 -> 0.16 | F15: =($Q$6-C15)^2 -> 0.33222415 | I15: SUM Opportunities | J15: =SUM(I3:I12) -> 144 | K15: Kiểm tra Calibration Table đúng
A16: ='Analysis 2 — Hypothesis Testing'!A15 -> Lost | B16: ='Analysis 2 — Hypothesis Testing'!B15 -> 20 | C16: =IF(A16="Won",1,0) -> 0 | D16: =B16/100 -> 0.2 | E16: =(D16-C16)^2 -> 0.04 | F16: =($Q$6-C16)^2 -> 0.33222415 | I16: SUM Won | J16: =SUM(J3:J12) -> 83 | Q16: Ý nghĩa:
A17: ='Analysis 2 — Hypothesis Testing'!A16 -> Lost | B17: ='Analysis 2 — Hypothesis Testing'!B16 -> 40 | C17: =IF(A17="Won",1,0) -> 0 | D17: =B17/100 -> 0.4 | E17: =(D17-C17)^2 -> 0.16 | F17: =($Q$6-C17)^2 -> 0.33222415 | I17: SUM Lost | J17: =SUM(K3:K12) -> 61 | Q17: > 0 → tốt hơn baseline
A18: ='Analysis 2 — Hypothesis Testing'!A17 -> Lost | B18: ='Analysis 2 — Hypothesis Testing'!B17 -> 30 | C18: =IF(A18="Won",1,0) -> 0 | D18: =B18/100 -> 0.3 | E18: =(D18-C18)^2 -> 0.09 | F18: =($Q$6-C18)^2 -> 0.33222415 | Q18: = 0 → bằng baseline
A19: ='Analysis 2 — Hypothesis Testing'!A18 -> Lost | B19: ='Analysis 2 — Hypothesis Testing'!B18 -> 50 | C19: =IF(A19="Won",1,0) -> 0 | D19: =B19/100 -> 0.5 | E19: =(D19-C19)^2 -> 0.25 | F19: =($Q$6-C19)^2 -> 0.33222415 | Q19: < 0 → kém hơn baseline
A20: ='Analysis 2 — Hypothesis Testing'!A19 -> Lost | B20: ='Analysis 2 — Hypothesis Testing'!B19 -> 40 | C20: =IF(A20="Won",1,0) -> 0 | D20: =B20/100 -> 0.4 | E20: =(D20-C20)^2 -> 0.16 | F20: =($Q$6-C20)^2 -> 0.33222415 | Q20: → CRM Probability kém hơn baseline về Brier Score.
A21: ='Analysis 2 — Hypothesis Testing'!A20 -> Lost | B21: ='Analysis 2 — Hypothesis Testing'!B20 -> 40 | C21: =IF(A21="Won",1,0) -> 0 | D21: =B21/100 -> 0.4 | E21: =(D21-C21)^2 -> 0.16 | F21: =($Q$6-C21)^2 -> 0.33222415
A22: ='Analysis 2 — Hypothesis Testing'!A21 -> Lost | B22: ='Analysis 2 — Hypothesis Testing'!B21 -> 40 | C22: =IF(A22="Won",1,0) -> 0 | D22: =B22/100 -> 0.4 | E22: =(D22-C22)^2 -> 0.16 | F22: =($Q$6-C22)^2 -> 0.33222415
A23: ='Analysis 2 — Hypothesis Testing'!A22 -> Lost | B23: ='Analysis 2 — Hypothesis Testing'!B22 -> 40 | C23: =IF(A23="Won",1,0) -> 0 | D23: =B23/100 -> 0.4 | E23: =(D23-C23)^2 -> 0.16 | F23: =($Q$6-C23)^2 -> 0.33222415
A24: ='Analysis 2 — Hypothesis Testing'!A23 -> Lost | B24: ='Analysis 2 — Hypothesis Testing'!B23 -> 40 | C24: =IF(A24="Won",1,0) -> 0 | D24: =B24/100 -> 0.4 | E24: =(D24-C24)^2 -> 0.16 | F24: =($Q$6-C24)^2 -> 0.33222415
A25: ='Analysis 2 — Hypothesis Testing'!A24 -> Lost | B25: ='Analysis 2 — Hypothesis Testing'!B24 -> 20 | C25: =IF(A25="Won",1,0) -> 0 | D25: =B25/100 -> 0.2 | E25: =(D25-C25)^2 -> 0.04 | F25: =($Q$6-C25)^2 -> 0.33222415
A26: ='Analysis 2 — Hypothesis Testing'!A25 -> Lost | B26: ='Analysis 2 — Hypothesis Testing'!B25 -> 70 | C26: =IF(A26="Won",1,0) -> 0 | D26: =B26/100 -> 0.7 | E26: =(D26-C26)^2 -> 0.49 | F26: =($Q$6-C26)^2 -> 0.33222415
A27: ='Analysis 2 — Hypothesis Testing'!A26 -> Lost | B27: ='Analysis 2 — Hypothesis Testing'!B26 -> 60 | C27: =IF(A27="Won",1,0) -> 0 | D27: =B27/100 -> 0.6 | E27: =(D27-C27)^2 -> 0.36 | F27: =($Q$6-C27)^2 -> 0.33222415
A28: ='Analysis 2 — Hypothesis Testing'!A27 -> Lost | B28: ='Analysis 2 — Hypothesis Testing'!B27 -> 30 | C28: =IF(A28="Won",1,0) -> 0 | D28: =B28/100 -> 0.3 | E28: =(D28-C28)^2 -> 0.09 | F28: =($Q$6-C28)^2 -> 0.33222415
A29: ='Analysis 2 — Hypothesis Testing'!A28 -> Lost | B29: ='Analysis 2 — Hypothesis Testing'!B28 -> 90 | C29: =IF(A29="Won",1,0) -> 0 | D29: =B29/100 -> 0.9 | E29: =(D29-C29)^2 -> 0.81 | F29: =($Q$6-C29)^2 -> 0.33222415
A30: ='Analysis 2 — Hypothesis Testing'!A29 -> Lost | B30: ='Analysis 2 — Hypothesis Testing'!B29 -> 60 | C30: =IF(A30="Won",1,0) -> 0 | D30: =B30/100 -> 0.6 | E30: =(D30-C30)^2 -> 0.36 | F30: =($Q$6-C30)^2 -> 0.33222415
A31: ='Analysis 2 — Hypothesis Testing'!A30 -> Lost | B31: ='Analysis 2 — Hypothesis Testing'!B30 -> 70 | C31: =IF(A31="Won",1,0) -> 0 | D31: =B31/100 -> 0.7 | E31: =(D31-C31)^2 -> 0.49 | F31: =($Q$6-C31)^2 -> 0.33222415
A32: ='Analysis 2 — Hypothesis Testing'!A31 -> Lost | B32: ='Analysis 2 — Hypothesis Testing'!B31 -> 40 | C32: =IF(A32="Won",1,0) -> 0 | D32: =B32/100 -> 0.4 | E32: =(D32-C32)^2 -> 0.16 | F32: =($Q$6-C32)^2 -> 0.33222415
... A36: ='Analysis 2 — Hypothesis Testing'!A35 -> Lost | B36: ='Analysis 2 — Hypothesis Testing'!B35 -> 20 | C36: =IF(A36="Won",1,0) -> 0 | D36: =B36/100 -> 0.2 | E36: =(D36-C36)^2 -> 0.04 | F36: =($Q$6-C36)^2 -> 0.33222415
A37: ='Analysis 2 — Hypothesis Testing'!A36 -> Lost | B37: ='Analysis 2 — Hypothesis Testing'!B36 -> 40 | C37: =IF(A37="Won",1,0) -> 0 | D37: =B37/100 -> 0.4 | E37: =(D37-C37)^2 -> 0.16 | F37: =($Q$6-C37)^2 -> 0.33222415 | H37: Insight
A38: ='Analysis 2 — Hypothesis Testing'!A37 -> Lost | B38: ='Analysis 2 — Hypothesis Testing'!B37 -> 50 | C38: =IF(A38="Won",1,0) -> 0 | D38: =B38/100 -> 0.5 | E38: =(D38-C38)^2 -> 0.25 | F38: =($Q$6-C38)^2 -> 0.33222415
A39: ='Analysis 2 — Hypothesis Testing'!A38 -> Lost | B39: ='Analysis 2 — Hypothesis Testing'!B38 -> 50 | C39: =IF(A39="Won",1,0) -> 0 | D39: =B39/100 -> 0.5 | E39: =(D39-C39)^2 -> 0.25 | F39: =($Q$6-C39)^2 -> 0.33222415 | H39: Trường Probability cho thấy độ hiệu chuẩn kém khi xét trên dữ liệu các cơ hội đã chốt. Tỷ lệ thắng thực tế thường xuyên sai lệch so với các mức xác suất được gán; cụ thể, chỉ số Brier của trường Probability này là khoảng 0,303, trong khi chỉ số tương ứng của mô hình tham chiếu cơ sở (dựa trên tỷ lệ WON chung) là 0,244. Điều này cho thấy trường Probability hiện tại có thể không cung cấp sự đáng tin cậy phục vụ việc dự báo.
A40: ='Analysis 2 — Hypothesis Testing'!A39 -> Lost | B40: ='Analysis 2 — Hypothesis Testing'!B39 -> 40 | C40: =IF(A40="Won",1,0) -> 0 | D40: =B40/100 -> 0.4 | E40: =(D40-C40)^2 -> 0.16 | F40: =($Q$6-C40)^2 -> 0.33222415
A41: ='Analysis 2 — Hypothesis Testing'!A40 -> Lost | B41: ='Analysis 2 — Hypothesis Testing'!B40 -> 100 | C41: =IF(A41="Won",1,0) -> 0 | D41: =B41/100 -> 1 | E41: =(D41-C41)^2 -> 1 | F41: =($Q$6-C41)^2 -> 0.33222415
A42: ='Analysis 2 — Hypothesis Testing'!A41 -> Lost | B42: ='Analysis 2 — Hypothesis Testing'!B41 -> 40 | C42: =IF(A42="Won",1,0) -> 0 | D42: =B42/100 -> 0.4 | E42: =(D42-C42)^2 -> 0.16 | F42: =($Q$6-C42)^2 -> 0.33222415
A43: ='Analysis 2 — Hypothesis Testing'!A42 -> Lost | B43: ='Analysis 2 — Hypothesis Testing'!B42 -> 70 | C43: =IF(A43="Won",1,0) -> 0 | D43: =B43/100 -> 0.7 | E43: =(D43-C43)^2 -> 0.49 | F43: =($Q$6-C43)^2 -> 0.33222415 | H43: Lưu ý
A44: ='Analysis 2 — Hypothesis Testing'!A43 -> Lost | B44: ='Analysis 2 — Hypothesis Testing'!B43 -> 30 | C44: =IF(A44="Won",1,0) -> 0 | D44: =B44/100 -> 0.3 | E44: =(D44-C44)^2 -> 0.09 | F44: =($Q$6-C44)^2 -> 0.33222415 | H44: Kết quả có thể không chính xác do các giá trị Probability có mẫu nhỏ (80% và 100%)
A45: ='Analysis 2 — Hypothesis Testing'!A44 -> Lost | B45: ='Analysis 2 — Hypothesis Testing'!B44 -> 70 | C45: =IF(A45="Won",1,0) -> 0 | D45: =B45/100 -> 0.7 | E45: =(D45-C45)^2 -> 0.49 | F45: =($Q$6-C45)^2 -> 0.33222415
A46: ='Analysis 2 — Hypothesis Testing'!A45 -> Lost | B46: ='Analysis 2 — Hypothesis Testing'!B45 -> 30 | C46: =IF(A46="Won",1,0) -> 0 | D46: =B46/100 -> 0.3 | E46: =(D46-C46)^2 -> 0.09 | F46: =($Q$6-C46)^2 -> 0.33222415
A47: ='Analysis 2 — Hypothesis Testing'!A46 -> Lost | B47: ='Analysis 2 — Hypothesis Testing'!B46 -> 90 | C47: =IF(A47="Won",1,0) -> 0 | D47: =B47/100 -> 0.9 | E47: =(D47-C47)^2 -> 0.81 | F47: =($Q$6-C47)^2 -> 0.33222415
A48: ='Analysis 2 — Hypothesis Testing'!A47 -> Lost | B48: ='Analysis 2 — Hypothesis Testing'!B47 -> 30 | C48: =IF(A48="Won",1,0) -> 0 | D48: =B48/100 -> 0.3 | E48: =(D48-C48)^2 -> 0.09 | F48: =($Q$6-C48)^2 -> 0.33222415
A49: ='Analysis 2 — Hypothesis Testing'!A48 -> Lost | B49: ='Analysis 2 — Hypothesis Testing'!B48 -> 40 | C49: =IF(A49="Won",1,0) -> 0 | D49: =B49/100 -> 0.4 | E49: =(D49-C49)^2 -> 0.16 | F49: =($Q$6-C49)^2 -> 0.33222415
A50: ='Analysis 2 — Hypothesis Testing'!A49 -> Lost | B50: ='Analysis 2 — Hypothesis Testing'!B49 -> 70 | C50: =IF(A50="Won",1,0) -> 0 | D50: =B50/100 -> 0.7 | E50: =(D50-C50)^2 -> 0.49 | F50: =($Q$6-C50)^2 -> 0.33222415
A51: ='Analysis 2 — Hypothesis Testing'!A50 -> Lost | B51: ='Analysis 2 — Hypothesis Testing'!B50 -> 80 | C51: =IF(A51="Won",1,0) -> 0 | D51: =B51/100 -> 0.8 | E51: =(D51-C51)^2 -> 0.64 | F51: =($Q$6-C51)^2 -> 0.33222415
A52: ='Analysis 2 — Hypothesis Testing'!A51 -> Lost | B52: ='Analysis 2 — Hypothesis Testing'!B51 -> 10 | C52: =IF(A52="Won",1,0) -> 0 | D52: =B52/100 -> 0.1 | E52: =(D52-C52)^2 -> 0.01 | F52: =($Q$6-C52)^2 -> 0.33222415
A53: ='Analysis 2 — Hypothesis Testing'!A52 -> Lost | B53: ='Analysis 2 — Hypothesis Testing'!B52 -> 20 | C53: =IF(A53="Won",1,0) -> 0 | D53: =B53/100 -> 0.2 | E53: =(D53-C53)^2 -> 0.04 | F53: =($Q$6-C53)^2 -> 0.33222415
A54: ='Analysis 2 — Hypothesis Testing'!A53 -> Lost | B54: ='Analysis 2 — Hypothesis Testing'!B53 -> 30 | C54: =IF(A54="Won",1,0) -> 0 | D54: =B54/100 -> 0.3 | E54: =(D54-C54)^2 -> 0.09 | F54: =($Q$6-C54)^2 -> 0.33222415
A55: ='Analysis 2 — Hypothesis Testing'!A54 -> Lost | B55: ='Analysis 2 — Hypothesis Testing'!B54 -> 20 | C55: =IF(A55="Won",1,0) -> 0 | D55: =B55/100 -> 0.2 | E55: =(D55-C55)^2 -> 0.04 | F55: =($Q$6-C55)^2 -> 0.33222415
A56: ='Analysis 2 — Hypothesis Testing'!A55 -> Lost | B56: ='Analysis 2 — Hypothesis Testing'!B55 -> 30 | C56: =IF(A56="Won",1,0) -> 0 | D56: =B56/100 -> 0.3 | E56: =(D56-C56)^2 -> 0.09 | F56: =($Q$6-C56)^2 -> 0.33222415
... A146: ='Analysis 2 — Hypothesis Testing'!A145 -> Won | B146: ='Analysis 2 — Hypothesis Testing'!B145 -> 30 | C146: =IF(A146="Won",1,0) -> 1 | D146: =B146/100 -> 0.3 | E146: =(D146-C146)^2 -> 0.49 | F146: =($Q$6-C146)^2 -> 0.17944637

Sheet Business Recommendation
B3: Business Recommendation
B6: 1 | C6: Không sử dụng Probability như một xác suất thắng chính xác trong việc dự báo.
B7: 2 | C7: Không dựa riêng vào Probability để ưu tiên sales opportunities.
B8: 3 | C8: Kiểm tra lại cách Probability đang được tạo.
B9: 4 | C9: Đợi thêm thời gian để thu thập thêm closed opportunities nhằm tăng độ tin cậy của calibration analysis.
